Workbook
Name FINISHES_NET_TOTAL: 'Finishes Cover'!$F$30
Name FINISHES_GRAND_TOTAL: 'Finishes Cover'!$F$36
Name ICF_PACKAGE_TOTAL: 'Finishes Cover'!$F$39
Name COMBINED_TOTAL: 'Finishes Cover'!$F$40

Sheet Cover
A10: BILL OF QUANTITIES
A11: ICF KIT · CONCRETE · LABOUR
A14: PLOT 1 RIVENDELL PARK, DOUGLAS
A15: Single Dwelling with Basement + ICF Pool Tank · Douglas, Lanark, South Lanarkshire ML11 8EB · SCOTLAND
B17: Quotation Reference | C17: ES26-084
B18: Project | C18: Plot 1 Rivendell Park, Douglas
B19: House Type | C19: Single dwelling: 10in Std basement + pool tank, 6in XR35 GF (cores aligned), RC slabs, vaulted cut roof
B20: Client | C20: Mr K & Mrs Burrell
B21: Site Address | C21: New Dwelling at Plot 1 Rivendell Park, Douglas, Lanark, South Lanarkshire ML11 8EB
B22: BOQ Issued | C22: 20 October 2026
B23: BOQ Reference | C23: BOQ-ES26-084-001 · Revision 1.0
B24: Prepared by | C24: Tom Smith — BuildEase Manager, Nudura UK
B25: Issued by | C25: Tremco Construction Products Group
B26: Currency | C26: Pound Sterling (GBP) · VAT at 20%
B27: Measurement Convention | C27: RICS New Rules of Measurement (NRM2)
B29: IMPORTANT NOTICE — DISCLAIMER
B30: • This Bill of Quantities is supplied in good faith based on the BuildEase take-off models for Plot 1 Rivendell Park, Douglas and the associated Tremco CPG quotation.
B31: • ALL QUANTITIES SHOULD BE INDEPENDENTLY CHECKED AND VERIFIED BY THE PROJECT QS / QUANTITY SURVEYOR before tender submission, ordering or contract award.
B32: • This BOQ does NOT include an external render / finish allowance. Any render, coatings or external wall finish must be measured and priced separately.
B33: • Section C (Concrete) volumes are geometric voids — allow ~3% web displacement deduction and ~5% wastage on top when ordering ready-mix.
B34: • Section D (Labour) day estimates are scaled proportionately from a reference project; actual gang productivity will vary with site conditions, weather and trade experience.
B35: • BuildEase, Tremco Construction Products Group and Nudura UK accept no liability for tender or contract outcomes arising from the use of these figures. If in doubt — ask.
B36: • Contact: Tom Smith — BuildEase Manager, Nudura UK — for clarification on any quantity or rate basis in this document.
A38: SCOTLAND: the design must satisfy the Building Standards (Scotland) technical handbooks (building warrant from South Lanarkshire Council) - not the English Approved Documents / LABC. Building height ~6.3 m above the ground floor (ridge) - below 11 m.
A39: NOT FOR CONSTRUCTION. The two "floor" slots of the programme and D.2 are RC slabs by others (basement raft, GF suspended slab); slab concrete, rebar and pumping are NOT in this ICF BOQ (coordination quantities in the finishes package Bill 6). Engineer to design: the GF slab over the pool and the garage, the 4.55 m garage door lintel, the vaulted roof ridge beams / posts and the glazed gables.

Sheet Contents
A1: CONTENTS
A4: Section | B4: Description | C4: Sheet | D4: Status
B5: Cover & Project Information | C5: Cover
B6: Contents | C6: Contents
B7: Indicative Programme (Gantt) | C7: Programme | D7: Information
B8: Summary of Tender Pricing | C8: Summary
A9: A | B9: Preliminaries | C9: A_Preliminaries | D9: Contractor priced
A10: B | B10: ICF Kit Supply | C10: B_ICF_Supply | D10: Pre-priced
A11: C | B11: Concrete Supply, Pump & Placement | C11: C_Concrete | D11: Contractor priced
A12: D | B12: Labour — ICF, Floors & Roofs | C12: D_Labour | D12: Contractor priced
A13: F | B13: Reference Data (informative only) | C13: F_Reference | D13: —

Sheet Programme
A1: PROG · INDICATIVE INSTALL PROGRAMME — RESOURCE-LEVELLED, ONE COLUMN PER WORKING DAY
A2: Group-by-group sequential build with a staggered start between groups. ICF install + snag + pour cycles, intermediate floors and roof structure are completed before moving on. Resourcing and durations below are indicative and must be validated by site management. Render / external finish is NOT included in this programme.
F3: W1 | M3: W2 | T3: W3 | AA3: W4 | AH3: W5
A4: Group | B4: Plots | C4: Forms | D4: Weeks | E4: Start wk | F4: M | G4: T | H4: W | I4: T | J4: F | K4: S | L4: S | M4: M | N4: T | O4: W | P4: T | Q4: F | R4: S | S4: S | T4: M | U4: T | V4: W | W4: T | X4: F | Y4: S | Z4: S | AA4: M | AB4: T | AC4: W | AD4: T | AE4: F | AF4: S | AG4: S | AH4: M | AI4: T | AJ4: W | AK4: T | AL4: F | AM4: S | AN4: S
A5: Plot 1 dwelling | B5: 1 | C5: 449 | D5: 5 | E5: 1
A7: LEGEND
C8: ICF walls — first lift: pool tank P (erection, snag & pour)
C9: ICF walls — basement BL (on the raft), master-suite footing FB and GF L1 (after the GF slab)
C10: Concrete pour — sized at 60 m3 per pump-day (1 day per lift here), ICF crew attends, pump on site
C11: Curing — pours held to Fridays where possible so the 2 curing days fall on the weekend; a mid-week pour cures 2 working days
C12: RC slab by others — basement raft after the pool tank; GF suspended slab after the basement (1 day each by Tom's rule)
C13: Vaulted roof structure (cut rafters on ridge beams), 1 day by Tom's rule
A15: RESOURCING
A16: • 1 ICF crews of 8 trained installers (each crew = 2 four-man gang-equivalents) erect the wall lifts, moving to the next ready block while a floor is fitted; 1 joinery crew of 3 fits every intermediate floor and roof (Tom's rule 19.10.26: floors 1 day per plot, roofs 1 day per plot - one plot; the two 'floors' here are RC slabs by others (basement raft, GF suspended slab), the roof is the vaulted cut roof). Programme is resource-levelled day by day (white = block waiting for a crew).
A17: • Total ICF site programme: 5 working weeks (ICF erection, floors and roofs). Section A Preliminaries are quantified against this 5-week programme.
A18: • EXTERNAL RENDER / FINISH IS EXCLUDED from this BOQ and this programme. Where a render system is later specified, allow a separate workstream — per BBA guidance, render cannot begin until the concrete core has cured for a minimum of 28 days after the final pour.
A19: • Concrete pump booked on the pour days for each group (see Section C).
A20: • Lead time for BuildEase Pre-Cut Service: 5–6 weeks from order placement; procurement runs in parallel with mobilisation.
A21: • Programme estimates are provided in good faith and must be verified by the project / site management team.
A22: • SCOTLAND: the design must satisfy the Building Standards (Scotland) technical handbooks (building warrant from South Lanarkshire Council) - not the English Approved Documents / LABC. Building height ~6.3 m above the ground floor (ridge) - below 11 m.
A23: • Tom's rule (19.10.26): floors 1 day PER PLOT, roofs 1 day PER PLOT - one plot here, so each RC slab slot and the vaulted roof are shown at 1 day. The floor rows of this programme are RC SLABS BY OTHERS (basement raft after the pool tank - groundworks / engineer; GF suspended slab after the basement - engineer / frame contractor), NOT timber joists; slab concrete, rebar, falsework and slab pumping are NOT in this ICF BOQ (coordination quantities in the finishes package Bill 6).
A24: • Build sequence (no client programme issued): pool tank P (3 courses, on the pool base slab) -> pour -> basement raft -> basement BL (8 courses) -> pour -> GF suspended slab -> master-suite footing FB (2 courses) -> pour -> GF L1 (14 courses incl. the raked gables) -> pour -> vaulted roof. The FB pour (~2.5 m3) could share the GF slab pump visit or the L1 pour to save a pump day - not assumed.
A25: • ICF pours sized at 60 m3 per pump per day from each lift's own concrete volume (all four ICF pours are 1 pump day each here).
A26: • PROGRAMME (BOQ Builder sheet 'Programme', 1 ICF crew of 8 + 1 joinery crew of 3, Tom's rule floors / roofs 1 day per plot, pours at 60 m3 / pump-day): 21 working days = 5 weeks. Sequence: ICF P d0-0.46; pour d1-2; cure d2-4; basement raft 300 RC d4-5; ICF BL d5-6.98; pour d9-10; GF suspended RC slab 250 d10-11; ICF FB d11-11.15; pour d14-15; ICF L1 d15-16.68; pour d19-20; vaulted roof structure d20-21. ICF concrete 98.32 m3 (geometric, ordered forms) in 4 pump days. ALIGNMENT: the proposal Rev B prices 3 stillages x 6 weeks hire (GBP 1,440.00); on this programme the alignment is needed from the first ICF lift (pool tank, day 0) to the last pour (GF L1, day 20) = 4 weeks on hire - 2 weeks LESS than priced (GBP 480.00 of hire not needed on this programme). SENSITIVITY: Tom's 1-day floor rule is written for timber floors; the two slabs here are RC (basement raft, GF suspended slab over the pool and the garage) - with 10 working days per slab for falsework / rebar / pour / cure before loading (engineer to confirm) the programme is 8 weeks and the alignment is on hire 8 weeks (+2 vs the 6 priced) unless it is off-hired between lifts. The proposal has NOT been changed - confirm the hire period with the client / site team.
A27: • Basement + pool tank concrete: mix / waterproofing admixture and waterstops to the BS 8102 waterproofing designer and the engineer.

Sheet Summary
A1: SUMMARY OF TENDER PRICING
A3: Section totals are carried forward from each Bill section. Pre-priced columns show values from the associated Tremco CPG quotation; contractor-priced columns populate automatically when rates are entered in the section sheets. This BOQ excludes external render.
A5: Section | B5: Description | C5: Pre-priced (£) | D5: Contractor-priced (£) | E5: Section Total (£)
A6: A | B6: Preliminaries | D6: ='A_Preliminaries'!F1000 | E6: =IF(ISNUMBER(C6),C6,0)+IF(ISNUMBER(D6),D6,0)
A7: B | B7: ICF Kit Supply | C7: 29139.75 | E7: =IF(ISNUMBER(C7),C7,0)+IF(ISNUMBER(D7),D7,0)
A8: C | B8: Concrete Supply, Pump & Placement | D8: ='C_Concrete'!F1000 | E8: =IF(ISNUMBER(C8),C8,0)+IF(ISNUMBER(D8),D8,0)
A9: D | B9: Labour — ICF, Floors & Roofs | D9: ='D_Labour'!F1000 | E9: =IF(ISNUMBER(C9),C9,0)+IF(ISNUMBER(D9),D9,0)
B11: NET TOTAL (excluding VAT) | C11: =SUM(C6:C9) | D11: =SUM(D6:D9) | E11: =SUM(E6:E9)
B12: VAT @ 20% | E12: =E11*0.20
B13: GRAND TOTAL (inclusive of VAT) | E13: =E11+E12
A17: SIGNATURES
A19: Priced by
A20: Tendered by
A21: Approved by

Sheet A_Preliminaries
A1: A · PRELIMINARIES
A2: Items priced per working week against the site programme total of 5 weeks (see Programme sheet). Quantities are pre-populated; the contractor inserts the weekly rate.
A4: Ref | B4: Description | C4: Unit | D4: Qty | E4: Rate (£) | F4: Total (£)
A5: A.1 | B5: Site set-up, fencing, signage, induction & welfare establishment | C5: item | D5: 1 | F5: =IF(AND(ISNUMBER(D5),ISNUMBER(E5)),D5*E5,0)
A6: A.2 | B6: Welfare facilities — canteen, drying, toilets (hire) | C6: wk | D6: 5 | F6: =IF(AND(ISNUMBER(D6),ISNUMBER(E6)),D6*E6,0)
A7: A.3 | B7: Contract management & site supervision | C7: wk | D7: 5 | F7: =IF(AND(ISNUMBER(D7),ISNUMBER(E7)),D7*E7,0)
A8: A.4 | B8: Health & Safety, RAMS, CDM consultancy | C8: wk | D8: 5 | F8: =IF(AND(ISNUMBER(D8),ISNUMBER(E8)),D8*E8,0)
A9: A.5 | B9: Public liability and contract works insurance | C9: item | D9: 1 | F9: =IF(AND(ISNUMBER(D9),ISNUMBER(E9)),D9*E9,0)
A10: A.6 | B10: Scaffolding — independent access for ICF erection | C10: wk | D10: 5 | F10: =IF(AND(ISNUMBER(D10),ISNUMBER(E10)),D10*E10,0)
A11: A.7 | B11: Plant hire — telehandler / forklift for offload & ICF moves | C11: wk | D11: 5 | F11: =IF(AND(ISNUMBER(D11),ISNUMBER(E11)),D11*E11,0)
A12: A.8 | B12: Plant hire — small tools, generators, power & lighting | C12: wk | D12: 5 | F12: =IF(AND(ISNUMBER(D12),ISNUMBER(E12)),D12*E12,0)
A13: A.9 | B13: Hoarding / site enclosure / security | C13: wk | D13: 5 | F13: =IF(AND(ISNUMBER(D13),ISNUMBER(E13)),D13*E13,0)
A14: A.10 | B14: Temporary services — water, power, lighting (hire) | C14: wk | D14: 5 | F14: =IF(AND(ISNUMBER(D14),ISNUMBER(E14)),D14*E14,0)
A15: A.11 | B15: Site clean, waste management & skip rotation | C15: wk | D15: 5 | F15: =IF(AND(ISNUMBER(D15),ISNUMBER(E15)),D15*E15,0)
A16: A.12 | B16: Setting out and surveying — engineer's level checks | C16: wk | D16: 5 | F16: =IF(AND(ISNUMBER(D16),ISNUMBER(E16)),D16*E16,0)
A17: A.13 | B17: Site take-down, hand-over & demobilisation | C17: item | D17: 1 | F17: =IF(AND(ISNUMBER(D17),ISNUMBER(E17)),D17*E17,0)
A18: A.14 | B18: Pre-completion sound test (Approved Document E) | C18: test | F18: =IF(AND(ISNUMBER(D18),ISNUMBER(E18)),D18*E18,0)
A19: A.15 | B19: Air-tightness test (Approved Document L) | C19: test | F19: =IF(AND(ISNUMBER(D19),ISNUMBER(E19)),D19*E19,0)
A20: A.16 | B20: Day works allowance | C20: sum | F20: =IF(AND(ISNUMBER(D20),ISNUMBER(E20)),D20*E20,0)
B22: A — PRELIMINARIES SUBTOTAL | F22: =SUM(F5:F20)
F1000: =F22

Sheet B_ICF_Supply
A1: B · ICF KIT SUPPLY
A2: ICF material supply values are pre-priced from the associated Tremco CPG quotation. Pre-cut service fees are taken from each BuildEase take-off.
A4: Ref | B4: Description | C4: Unit | D4: Qty | E4: Rate (£) | F4: Total (£)
A5: B.1 — ICF Block, Forms & Accessories
A6: B.1 | B6: ICF Materials — Plot 1 dwelling (1 plot(s), 449 forms) | C6: group | D6: 1 | E6: 24872.37 | F6: =IF(AND(ISNUMBER(D6),ISNUMBER(E6)),D6*E6,0)
A8: B.2 — BuildEase Pre-Cut Service Fee
A9: B.2 | B9: Pre-Cut Service — Plot 1 dwelling | C9: group | D9: 1 | E9: 1702.62 | F9: =IF(AND(ISNUMBER(D9),ISNUMBER(E9)),D9*E9,0)
A11: B.3 — Haulage
A12: B.3 | B12: Haulage to site — 2 loads: 2 x artic @ 170.8 mi (proposal Rev B delivery schedule: substructure, then GF) | C12: item | D12: 1 | E12: 1124.76 | F12: =IF(AND(ISNUMBER(D12),ISNUMBER(E12)),D12*E12,0)
A14: B.4 — Alignment System
A15: B.4 | B15: Alignment System Rental — Plot 1 dwelling (42 systems) | C15: group | D15: 1 | E15: 1440 | F15: =IF(AND(ISNUMBER(D15),ISNUMBER(E15)),D15*E15,0)
B17: B — ICF KIT SUPPLY SUBTOTAL | F17: =SUM(F5:F15)
F1000: =F17

Sheet C_Concrete
A1: C · CONCRETE SUPPLY, PUMP & PLACEMENT
A2: Volumes are geometric void calculations (block length × course height × core thickness). Allow ~3% for plastic web displacement and ~5% wastage when ordering. Rates to be inserted by the contractor.
A4: Ref | B4: Description | C4: Unit | D4: Qty | E4: Rate (£) | F4: Total (£)
A5: C.1 — Ready-Mix Concrete Supply (C28/35 typical to BS 8500; basement + pool tank mix / admixture to the BS 8102 designer)
A6: C.1 | B6: Ready-mix concrete — Plot 1 dwelling (1 plot(s), geometric void) | C6: m³ | D6: 98.32 | F6: =IF(AND(ISNUMBER(D6),ISNUMBER(E6)),D6*E6,0)
A8: C.2 — Concrete Pump Hire
A9: C.2 | B9: Boom pump hire — Plot 1 dwelling | C9: day | D9: 4 | F9: =IF(AND(ISNUMBER(D9),ISNUMBER(E9)),D9*E9,0)
A10: C.2 | B10: Pump mobilisation / demobilisation | C10: item | D10: 1 | F10: =IF(AND(ISNUMBER(D10),ISNUMBER(E10)),D10*E10,0)
A12: C.3 — Concrete Vibration & Placement Plant
A13: C.3 | B13: Internal poker vibrator hire — site duration | C13: wk | D13: 5 | F13: =IF(AND(ISNUMBER(D13),ISNUMBER(E13)),D13*E13,0)
A14: C.3 | B14: Concrete banksman / poker operator | C14: day | F14: =IF(AND(ISNUMBER(D14),ISNUMBER(E14)),D14*E14,0)
B16: C — CONCRETE SUBTOTAL | F16: =SUM(F5:F14)
F1000: =F16

Sheet D_Labour
A1: D · LABOUR — ICF INSTALL, FLOORS & ROOFS
A2: ICF install days scaled proportionately against the Maycroft reference (52.65 forms per gang-day). Rates below are per 4-man gang per day. Floor and roof allowances are taken per group from the project configuration.
A4: Ref | B4: Description | C4: Unit | D4: Qty | E4: Rate (£) | F4: Total (£)
A5: D.1 — ICF Install Gang
A6: D.1 | B6: ICF install — Plot 1 dwelling (449 forms ÷ 52.65 forms/day = 8.5 gang-days) | C6: gang-day | D6: 8.5 | F6: =IF(AND(ISNUMBER(D6),ISNUMBER(E6)),D6*E6,0)
A7: D.1 | B7: Snag, pour & cure attendance (30% allowance, project total) | C7: gang-day | D7: 2.6 | F7: =IF(AND(ISNUMBER(D7),ISNUMBER(E7)),D7*E7,0)
A9: D.2 — RC Slabs by Others (basement raft — groundworks; GF suspended slab — engineer / frame contractor): programme days, NOT ICF labour
A10: D.2 | B10: RC slabs by others (raft + GF slab; programme days) — Plot 1 dwelling (2 floors × 1 gang-days) | C10: gang-day | D10: 2 | F10: =IF(AND(ISNUMBER(D10),ISNUMBER(E10)),D10*E10,0)
A12: D.3 — Roof Structure Labour (vaulted cut roof: 63 x 220 C24 rafters @ 600 on ridge beams + 3 SHS posts)
A13: D.3 | B13: Roof structure — Plot 1 dwelling | C13: gang-day | D13: 1 | F13: =IF(AND(ISNUMBER(D13),ISNUMBER(E13)),D13*E13,0)
B15: D — LABOUR SUBTOTAL | F15: =SUM(F5:F13)
F1000: =F15

Sheet F_Reference
A1: F · REFERENCE DATA (informative only)
A2: Per-group quantities calculated from the BuildEase take-off models. Values feed into Sections C and D. Render is excluded from this BOQ.
A4: Group | B4: Plots | C4: Forms | D4: Concrete (m³) | E4: ICF install days | F4: Floor + Roof days | G4: Pre-cut (£)
A5: Plot 1 dwelling | B5: 1 | C5: 449 | D5: 98.32 | E5: 8.5 | F5: 3 | G5: 1702.62
A6: SITE | B6: 1 | C6: 449 | D6: 98.32 | E6: 8.5 | F6: 3 | G6: 1702.62
A9: PER-LIFT FORM BREAKDOWN
A10: Group | B10: Lift | C10: 4" Std | D10: 6" XR35 str | E10: 6" XR35 cnr | F10: 10" Std | G10: Lift total
A11: Plot 1 dwelling | B11: P | C11: 0 | D11: 0 | E11: 0 | F11: 48 | G11: 48
A12: Plot 1 dwelling | B12: BL | C12: 0 | D12: 0 | E12: 0 | F12: 208 | G12: 208
A13: Plot 1 dwelling | B13: FB | C13: 0 | D13: 12 | E13: 4 | F13: 0 | G13: 16
A14: Plot 1 dwelling | B14: L1 | C14: 0 | D14: 140 | E14: 37 | F14: 0 | G14: 177
A17: GEOMETRIC CONSTANTS & CALCULATION BASIS
A18: Block length | C18: 2.438 m | E18: 96 inches
A19: Course height | C19: 0.4574 m | E19: 18 inches
A20: 4" Std straight volume | C20: 0.1133 m³ | E20: =length × course × core
A21: 6" XR35 straight volume | C21: 0.1699 m³ | E21: =length × course × core
A22: 10" Std straight volume | C22: 0.2832 m³ | E22: =length × course × core
A23: 4" Std corner volume | C23: 0.0511 m³ | E23: L-void; long 31.625" / short 15.625"
A24: 6" XR35 corner volume | C24: 0.1133 m³ | E24: L-void; long 43" / short 27"
A25: Maycroft install rate | C25: 52.65 forms/day | E25: Reference: 1053 forms ÷ 20 days

Sheet Finishes Cover
C1: Bill of Quantities Package - Finishes & Ancillary Trades
C2: ES26-084 | Plot 1 Rivendell Park, Douglas | Mr K & Mrs Burrell
A4: DISCLAIMER: This information is supplied in good faith for guidance and coordination only. It is not part of the Nudura ICF price and must be checked and verified by the appropriate professional (quantity surveyor, designer, engineer or supplier) before use. Only the Nudura ICF formwork and associated accessories are included in our price. Quantities are measured from the BuildEase quotation model of the Foote McBride planning drawings (C2523 PP 01 001-008, raster, no sections / dimensions / levels - heights scaled from the elevations); no allowance for waste is included unless stated. Quantity columns are the model levels P / BL / FB / L1; the Site total is their sum. Rates and amounts are by others.
A6: Project | B6: Plot 1 Rivendell Park, Douglas
A7: Site | B7: New Dwelling at Plot 1 Rivendell Park, Douglas, Lanark, South Lanarkshire ML11 8EB
A8: Client | B8: Mr K & Mrs Burrell
A9: Architect | B9: Foote McBride Associates (C2523 PP 01 001-008, Jan 26, Council Approval - planning only)
A10: Quotation ref | B10: ES26-084
A11: Document | B11: Bill of Quantities Package - Finishes & Ancillary Trades
A12: Issue | B12: 01 (20/10/2026)
A13: Scope | B13: One dwelling: ICF pool tank (10in Std) + basement (10in Std, garage, laundry, stores, pool hall) + master-suite footing and GF (6in XR35, cores aligned), RC pool base / raft / GF suspended slab (by others), vaulted cut roof with ridge beams, raked feature glazing
A14: Building height | B14: SCOTLAND: the design must satisfy the Building Standards (Scotland) technical handbooks (building warrant from South Lanarkshire Council) - not the English Approved Documents / LABC. Building height ~6.3 m above the ground floor (ridge) - below 11 m.
A15: Engineer / specialists | B15: ENGINEER / SPECIALISTS TO DESIGN (all slabs, roof timbers, steel posts, glazing and partitions are in the model for coordination only): the GF suspended slab over the pool and the 7.5 m garage (and the three ridge-post point loads that land on it), the 4.55 m garage door lintel, the vaulted roof ridge beams (120 x 400 GL24h glulam on steel posts; 140 x 800 GL24h glulam), the glazed gables; BS 8102 basement waterproofing (specialist designer); the ICF pool tank (pool specialist). NOT FOR CONSTRUCTION.
A16: Prepared by | B16: BuildEase (Tremco CPG UK) - BuildEase Design Suite quotation model
A17: Status | B17: FOR INFORMATION, COORDINATION AND PRICING BY OTHERS - rates blank; NOT part of the Nudura ICF price; NOT FOR CONSTRUCTION
A19: PACKAGE OVERVIEW - pricing by others (all amounts formula-linked to each bill's Package Summary)
A20: Bill | B20: Package | C20: Code / NRM2 | D20: Supply £ | E20: Install £ | F20: Total £
A21: Bill 1 | B21: External Wall Finish to the ICF (render / cladding - spec TBC) | C21: EXT NRM2 15 / 21 | D21: ='Bill 1 External Finish'!K27 | E21: ='Bill 1 External Finish'!L27 | F21: ='Bill 1 External Finish'!M27
A22: Bill 2 | B22: Internal Linings - Walls, Vaulted Ceilings, Tape, Beads & Skim | C22: DRY NRM2 28 | D22: ='Bill 2 Internal Linings'!K40 | E22: ='Bill 2 Internal Linings'!L40 | F22: ='Bill 2 Internal Linings'!M40
A23: Bill 3 | B23: Internal Doors & Ironmongery | C23: JOI NRM2 24 | D23: ='Bill 3 Doors'!K29 | E23: ='Bill 3 Doors'!L29 | F23: ='Bill 3 Doors'!M29
A24: Bill 4 | B24: Joinery - Skirtings, Architraves, Window Boards & Stair | C24: JOI NRM2 22 | D24: ='Bill 4 Joinery'!K31 | E24: ='Bill 4 Joinery'!L31 | F24: ='Bill 4 Joinery'!M31
A25: Bill 5 | B25: Timber Stud Partitions (TLSTF) - Framing, Openings, Head Restraint & Fixings | C25: JOI NRM2 16 | D25: ='Bill 5 Partitions'!K43 | E25: ='Bill 5 Partitions'!L43 | F25: ='Bill 5 Partitions'!M43
A26: Bill 6 | B26: Substructure & Slabs - Pool Base, Raft, GF Slab, Floor Build-ups (coordination) | C26: RCF / FLR NRM2 11 | D26: ='Bill 6 Slabs'!K33 | E26: ='Bill 6 Slabs'!L33 | F26: ='Bill 6 Slabs'!M33
A27: Bill 7 | B27: Vaulted Roof - Structure, Covering, Rainwater & Insulation | C27: RFS / RFC NRM2 16 / 18 | D27: ='Bill 7 Roof'!K49 | E27: ='Bill 7 Roof'!L49 | F27: ='Bill 7 Roof'!M49
A28: Bill 8 | B28: Glazing, External Doors, Raked Feature Screens & Garage Door | C28: WIN / GLZ NRM2 25 | D28: ='Bill 8 Glazing'!K44 | E28: ='Bill 8 Glazing'!L44 | F28: ='Bill 8 Glazing'!M44
A29: Bill 9 | B29: Basement Waterproofing (BS 8102) & ICF Pool Tank - PROVISIONAL | C29: WPF / POOL NRM2 17 | D29: ='Bill 9 Waterproofing Pool'!K31 | E29: ='Bill 9 Waterproofing Pool'!L31 | F29: ='Bill 9 Waterproofing Pool'!M31
A30: GRAND TOTAL - finishes / ancillary trades, net (excl. VAT) | D30: =SUM(D21:D29) | E30: =SUM(E21:E29) | F30: =SUM(F21:F29)
A32: Optional additions (enter %; blank = 0) | C32: % | F32: Amount £
A33: Preliminaries | B33: on the finishes net grand total | F33: =(F30)*N(C33)
A34: Overheads & profit | B34: on net total + preliminaries | F34: =(F30+F33)*N(C34)
A35: Contingency | B35: on net total + preliminaries + OH&P | F35: =(F30+F33+F34)*N(C35)
A36: GRAND TOTAL finishes incl. preliminaries, OH&P and contingency (excl. VAT) | F36: =F30+F33+F34+F35
A38: ICF PACKAGE HOOK - BuildEase BOQ Builder (ICF kit, concrete, labour, preliminaries, programme)
A39: Nudura ICF package (BuildEase BOQ Builder sheets of this workbook: Summary NET TOTAL) | F39: ='Summary'!$E$11
A40: COMBINED TOTAL - finishes package (incl. additions) + ICF package, excl. VAT | F40: =F36+N(F39)
A41: Pale-yellow cells are the only inputs (rates on each bill sheet, percentages and the ICF hook here). Everything else is a locked formula (protection has no password). Schedules A to D are reference only and are not priced. Named cells: FINISHES_NET_TOTAL, FINISHES_GRAND_TOTAL, ICF_PACKAGE_TOTAL, COMBINED_TOTAL.
A43: IMPORTANT - This information is supplied in good faith for guidance and coordination only. It is not part of the Nudura ICF price and must be checked and verified by the appropriate professional (quantity surveyor, designer, engineer or supplier) before use. Only the Nudura ICF formwork and associated accessories are included in our price. Quantities are measured from the BuildEase quotation model of the Foote McBride planning drawings (C2523 PP 01 001-008, raster, no sections / dimensions / levels - heights scaled from the elevations); no allowance for waste is included unless stated. Quantity columns are the model levels P / BL / FB / L1; the Site total is their sum. Rates and amounts are by others.
A45: KEY QUANTITIES (site totals: one dwelling, levels P / BL / FB / L1, net; linked to the bills)
A46: External finish to the ICF (GF + exposed below FFL) | D46: ='Bill 1 External Finish'!H10+'Bill 1 External Finish'!H11 | E46: m2
A47: Wall linings (ICF faces, partitions, reveals) | D47: ='Bill 2 Internal Linings'!H10+'Bill 2 Internal Linings'!H11+'Bill 2 Internal Linings'!H12+'Bill 2 Internal Linings'!H13+'Bill 2 Internal Linings'!H14+'Bill 2 Internal Linings'!H15+'Bill 2 Internal Linings'!H16+'Bill 2 Internal Linings'!H17+'Bill 2 Internal Linings'!H18 | E47: m2
A48: Ceilings (basement + GF vaulted on the slope) | D48: ='Bill 2 Internal Linings'!H21+'Bill 2 Internal Linings'!H22+'Bill 2 Internal Linings'!H23+'Bill 2 Internal Linings'!H24 | E48: m2
A49: Skim coat | D49: ='Bill 2 Internal Linings'!H31 | E49: m2
A50: Internal doorsets | D50: ='Bill 3 Doors'!H10+'Bill 3 Doors'!H11+'Bill 3 Doors'!H12+'Bill 3 Doors'!H13+'Bill 3 Doors'!H14+'Bill 3 Doors'!H15+'Bill 3 Doors'!H16 | E50: nr
A51: Skirting | D51: ='Bill 4 Joinery'!H10 | E51: m
A52: Timber stud partitions (gross area) | D52: ='Bill 5 Partitions'!H10+'Bill 5 Partitions'!H11 | E52: m2
A53: Partition door openings formed | D53: ='Bill 5 Partitions'!H21+'Bill 5 Partitions'!H22+'Bill 5 Partitions'!H23+'Bill 5 Partitions'!H24+'Bill 5 Partitions'!H25+'Bill 5 Partitions'!H26+'Bill 5 Partitions'!H27 | E53: nr
A54: RC base / raft / GF slab (by others) | D54: ='Bill 6 Slabs'!H10+'Bill 6 Slabs'!H11+'Bill 6 Slabs'!H12 | E54: m3
A55: Rafters 63 x 220 C24 (total length) | D55: ='Bill 7 Roof'!H16 | E55: m
A56: Roof covering on the slope | D56: ='Bill 7 Roof'!H28 | E56: m2
A57: Windows (UPVC) | D57: ='Bill 8 Glazing'!H10+'Bill 8 Glazing'!H11+'Bill 8 Glazing'!H12+'Bill 8 Glazing'!H13+'Bill 8 Glazing'!H14+'Bill 8 Glazing'!H15+'Bill 8 Glazing'!H16 | E57: nr
A58: Raked feature screens (gross) | D58: ='Bill 8 Glazing'!H27+'Bill 8 Glazing'!H28+'Bill 8 Glazing'!H29+'Bill 8 Glazing'!H30 | E58: m2
A59: Below-ground ICF faces (Type A tanking) | D59: ='Bill 9 Waterproofing Pool'!H10 | E59: m2
A61: Document control
A62: Issue | B62: Description | C62: Date | D62: By / Status
A63: 01 | B63: First issue: finishes / ancillary-trades BOQ package for the Nudura ICF quotation Rev B (port of the ES26-052 / ES26-080 packages, per level P / BL / FB / L1 for one dwelling), merged with the BuildEase BOQ Builder ICF bill + programme. Live pricing workbook: rates blank for pricing by others; ICF_PACKAGE_TOTAL linked to the BOQ Builder NET TOTAL | C63: 20/10/2026 | D63: BuildEase - T. Smith / For information / pricing by others - NOT FOR CONSTRUCTION
A65: Contents
A66: Finishes Cover (this sheet) - overview
A67: General Notes
A68: Summary of Bills (section breakdown)
A69: Finishes Bill 1 External Finish
A70: Finishes Bill 2 Internal Lining
A71: Finishes Bill 3 Doors
A72: Finishes Bill 4 Joinery
A73: Finishes Bill 5 Partitions
A74: Finishes Bill 6 Slabs
A75: Finishes Bill 7 Roof
A76: Finishes Bill 8 Glazing
... A81: Schedule D Partitions (not priced)

Sheet General Notes
B1: General Notes, Measurement Basis, Assumptions & Exclusions
B2: ES26-084 | Plot 1 Rivendell Park, Douglas | Mr K & Mrs Burrell
A4: DISCLAIMER: This information is supplied in good faith for guidance and coordination only. It is not part of the Nudura ICF price and must be checked and verified by the appropriate professional (quantity surveyor, designer, engineer or supplier) before use. Only the Nudura ICF formwork and associated accessories are included in our price. Quantities are measured from the BuildEase quotation model of the Foote McBride planning drawings (C2523 PP 01 001-008, raster, no sections / dimensions / levels - heights scaled from the elevations); no allowance for waste is included unless stated. Quantity columns are the model levels P / BL / FB / L1; the Site total is their sum. Rates and amounts are by others.
A6: 1 Purpose, status, Scotland and building height
A7: 1.1 | B7: SCOTLAND: the design must satisfy the Building Standards (Scotland) technical handbooks (building warrant from South Lanarkshire Council) - not the English Approved Documents / LABC. Building height ~6.3 m above the ground floor (ridge) - below 11 m.
A8: 1.2 | B8: ENGINEER / SPECIALISTS TO DESIGN (all slabs, roof timbers, steel posts, glazing and partitions are in the model for coordination only): the GF suspended slab over the pool and the 7.5 m garage (and the three ridge-post point loads that land on it), the 4.55 m garage door lintel, the vaulted roof ridge beams (120 x 400 GL24h glulam on steel posts; 140 x 800 GL24h glulam), the glazed gables; BS 8102 basement waterproofing (specialist designer); the ICF pool tank (pool specialist). NOT FOR CONSTRUCTION.
A9: 1.3 | B9: This package presents the finishes and ancillary-trade quantities measured by BuildEase alongside the Nudura ICF quotation for Plot 1 Rivendell Park, Douglas (ref ES26-084). It is set out as a Bill of Quantities so that the client, their quantity surveyor and trade contractors can price and coordinate the works.
A10: 1.4 | B10: Status: FOR INFORMATION, COORDINATION AND PRICING BY OTHERS - NOT FOR CONSTRUCTION. Supply and install rates are left blank deliberately - BuildEase / Tremco CPG are not pricing these trades. The Excel workbook is a live pricing document: enter rates and every amount, subtotal and total updates by formula.
A11: 1.5 | B11: The ICF kit, concrete core, pumping, ICF / floor / roof labour and the build programme are in the BuildEase BOQ Builder sheets of this workbook (Cover / Programme / Summary / A-F). The finishes cover carries a named hook (ICF_PACKAGE_TOTAL) linked to that NET TOTAL.
A12: 1.6 | B12: PROGRAMME (BOQ Builder sheet 'Programme', 1 ICF crew of 8 + 1 joinery crew of 3, Tom's rule floors / roofs 1 day per plot, pours at 60 m3 / pump-day): 21 working days = 5 weeks. Sequence: ICF P d0-0.46; pour d1-2; cure d2-4; basement raft 300 RC d4-5; ICF BL d5-6.98; pour d9-10; GF suspended RC slab 250 d10-11; ICF FB d11-11.15; pour d14-15; ICF L1 d15-16.68; pour d19-20; vaulted roof structure d20-21. ICF concrete 98.32 m3 (geometric, ordered forms) in 4 pump days. ALIGNMENT: the proposal Rev B prices 3 stillages x 6 weeks hire (GBP 1,440.00); on this programme the alignment is needed from the first ICF lift (pool tank, day 0) to the last pour (GF L1, day 20) = 4 weeks on hire - 2 weeks LESS than priced (GBP 480.00 of hire not needed on this programme). SENSITIVITY: Tom's 1-day floor rule is written for timber floors; the two slabs here are RC (basement raft, GF suspended slab over the pool and the garage) - with 10 working days per slab for falsework / rebar / pour / cure before loading (engineer to confirm) the programme is 8 weeks and the alignment is on hire 8 weeks (+2 vs the 6 priced) unless it is off-hired between lifts. The proposal has NOT been changed - confirm the hire period with the client / site team.
A13: 1.7 | B13: This information is supplied in good faith for guidance and coordination only. It is not part of the Nudura ICF price and must be checked and verified by the appropriate professional (quantity surveyor, designer, engineer or supplier) before use. Only the Nudura ICF formwork and associated accessories are included in our price.
A14: 1.8 | B14: Quantities are measured from the BuildEase quotation model of the Foote McBride planning drawings (C2523 PP 01 001-008, raster, no sections / dimensions / levels - heights scaled from the elevations); no allowance for waste is included unless stated. Quantity columns are the model levels P / BL / FB / L1; the Site total is their sum. Rates and amounts are by others.
A16: 2 Basis of measurement
A17: 2.1 | B17: Measured generally in accordance with the principles of NRM2 (RICS New Rules of Measurement): work measured net as fixed in position, grouped by work section, units m / m2 / m3 / t / nr / item. NRM2 is referenced for structure only; descriptions are BuildEase's own.
A18: 2.2 | B18: Quantities are NET. No allowance for waste, laps, cutting or breakage is included unless stated; an "Order guide" with a stated waste % is guidance only.
A19: 2.3 | B19: Quantity columns: one column PER MODEL LEVEL - P pool tank, BL basement, FB master-suite footing, L1 ground floor. One dwelling: the Site total is the sum of the levels (multiplier 1) and is a live formula.
A20: 2.4 | B20: Sources: Foote McBride C2523 PP 01 001-008 (planning proposals, raster, Council Approval - planning only: no sections, dimensions or levels; heights and ground lines scaled from the elevations at 1:100); the BuildEase quotation model 03_Models/KB_build.skp through its specs (04_Logs/specs KB_spec.json, KB_slabs.json, KB_partitions.json), build reports (04_Logs/build: fbw_fit, floors, struct, TLSTF walls / doors / verify / rake / pattress / head-restraint) and the Report Tool component export (04_Logs/takeoff/KB_components.json: the inner / outer EPS face areas of the 588 modelled forms, openings net). Measured offline by 05_Scripts/kb_boq.py (no live model).
A22: 3 Assumptions
A23: 3.1 | B23: Walls: basement + pool tank 10in Std (387.4 overall), GF + master-suite footing 6in XR35 (355.6), cores centre-aligned. Frames tight to the back of the outer EPS (101.8 GF / 66.8 basement): internal reveal 211 GF / 278 basement.
A24: 3.2 | B24: Levels: GF FFL 0; basement FFL -3,300 (8 courses from -3,658); pool floor ~-4,800, pool walls from -5,029; FB -914 to 0; GF 14 courses to 6,401 (plate 2,286, gables raked at 45 deg, ridges ~6.0 m). GF slab top -75 (soffit -325) + 75 screed.
A25: 3.3 | B25: External finish: generic "render or cladding, spec TBC" (the elevations read show no wall hatch). Exposed below-FFL faces from ground lines scaled off the elevation renders (+-150): garage apron ~3.26 below FFL, west 3.31 falling to 2.71, east ~1.23, wing front ~0.9-1.1, rear terrace at DPC.
A26: 3.4 | B26: GF ceilings are vaulted throughout (plasterboard on the rafters, measured on the 45 deg slope); the GF partitions are raked to the vault (TLSTF rake profiles). Basement ceilings are the GF slab soffit; the garage ceiling / partitions are fire-resisting (warrant); the pool hall is by the pool specialist.
A27: 3.5 | B27: Internal doors: 13 from the TLSTF door report; leaves the largest standard 1,981 leaf that fits the opening less 68. Wet rooms from the pattress reports. Partitions: TLSTF 38 x 89 C16 at 600 (400 wet) - BF 8 walls 31.4 m / GF 20 walls 43.0 m = 74.4 m, 13 door openings.
A28: 3.6 | B28: Roof: rafters counted at 600 c/c between the gable walls (Roof L 35 per slope over 20.4 m, Roof R 20 per slope over 12.0 m), lengths on the 45 deg slope from the ridge face to the eaves overhang / valley; 5 rooflights read off the east elevation; covering 367.1 m2 on the slope.
A29: 3.7 | B29: Raked glazing: sills G01 / G03a at FFL, G05 at -960 (entrance), G02R on the dining bi-fold head (2,075); areas from the fbw_fit head profiles.
A31: 4 Exclusions (not measured in this package)
A32: 4.1 | B32: Nudura ICF formwork and accessories (in the Nudura price). ICF wall concrete, pumping, ICF / floor / roof labour and preliminaries are in the BOQ Builder sheets.
A33: 4.2 | B33: Supply of windows, doors, screens and the garage door are listed for pricing by the window / glazing / door suppliers (Bill 8) - not by BuildEase. Chimney / flue, external works, drainage, retaining walls beyond the house, landscaping.
A34: 4.3 | B34: Floor finishes, decorations, kitchens, sanitaryware, M&E services (UFH pipework, pool plant, MVHR / dehumidification) and builder's work.
A35: 4.4 | B35: Fire-stopping and fire-rated service penetrations, sealants and mastics, except where expressly described.
A37: 5 Open items / to be confirmed
A38: 5.1 | B38: STRUCTURAL ENGINEER: GF suspended slab over the pool and the 7.5 m garage incl. the three ridge-post point loads that land on it over the pool tank (Bill 6C.1); the 4.55 m garage door lintel under the lounge front wall; the vaulted roof ridge beams (120 x 400 GL24h on SHS posts; 140 x 800 GL24h glulam, rear bearing on the glazed dining gable); the glazed gables; the ICF pool tank; tall raked GF partitions (studs to ~5.8 m).
A39: 5.2 | B39: BS 8102 WATERPROOFING SPECIALIST: basement (Grade 3, habitable + pool hall) - system choice, Types A / B / C, sump and pumps, land drain (Bill 9A, provisional).
A40: 5.3 | B40: POOL SPECIALIST: pool depth (1.5 m assumed - outline only on the drawings), tanking / finish, coping, plant, pool hall environment and its linings / ceiling (Bills 2A.3, 2B.3, 9B).
A41: 5.4 | B41: GARAGE DOOR SUPPLIER: 4,555 x 2,394 sectional door (Bill 8E.2, provisional - not fitted in the model).
A42: 5.5 | B42: GLAZING SPECIALIST: the raked feature screens to the vault / glazed gables G01, G02R, G03a, G05 (Bill 8D) - design, wind load, mullions, safety glass, support of the glazed dining gable under the glulam ridge.
A43: 5.6 | B43: ARCHITECT / WARRANT (Building Standards (Scotland)): guarding to the floor-length windows where the ground is > 600 mm below (Standard 4.4, 8E.1); safety glazing (4.8); internal door widths (4.2 - the 680 / 762 openings); garage / dwelling fire separation (Section 2: doors, partitions, ceiling); noise between rooms (5.2); energy / U-values (Section 6); external finish specification (Bill 1).
A44: 5.7 | B44: Basement level: modelled AS DRAWN at FFL -3,300 (~3.27 m below GF FFL at the garage) - Tom had chosen "3.0 m" from a misread; the laundry door threshold is drawn 620 above the basement FFL (internal step) - confirm.
A45: 5.8 | B45: Not modelled (items flagged, not measured): chimney / stove flue (lounge west wall), the 5 rooflights (east slope, Bill 7B.9 counted from the elevation), the basement pool hall / hall glazed screen, the basement stair, the basement garage nib (0.6 m).
A46: 5.9 | B46: fbw_fit.json "glass_m2" for the raked screens under-reports the glass by about half (pane polygon vertex averaging in kb_windows.rb) - this BOQ re-measures from the head profiles (Schedule B lists both).
A48: 6 What IS in the Nudura price (Quotation ES26-084 Rev B, NET GBP 29,139.75)
A49: 6.1 | B49: Nudura ICF kit as modelled in the BuildEase Design Suite: 588 forms modelled / 449 to order (P 51 / BL 258 / FB 17 / L1 262 modelled), materials GBP 24,872.37.
A50: 6.2 | B50: Accessories: VJC clips, end caps, Form-Lock, T-form support straps, lintel closures, spray foam.
A51: 6.3 | B51: BuildEase Pre-Cut Service GBP 1,702.62; alignment system 3 stillages x 6 weeks hire GBP 1,440.00; haulage 2 loads: 2 x artic @ 170.8 mi GBP 1,124.76.
A52: 6.4 | B52: Nothing in Bills 1 to 9 of this finishes package is included in the Nudura price.
A54: 7 Pricing instructions to tenderers
A55: 7.1 | B55: Each bill item has a SUPPLY rate and an INSTALL rate. Insert rates only in the pale-yellow cells of the Excel workbook: Supply = Site total qty x Supply rate; Install = Site total qty x Install rate; Line total = Supply + Install. Items measured as "item" are lump sums: the rate entered is the amount.
A56: 7.2 | B56: Each bill ends with a Package Summary (section subtotals for Supply / Install / Total and the package total). The Cover carries the full overview: one row per bill, grand totals, optional Preliminaries, Overheads & profit and Contingency percentages (pale-yellow cells; blank = 0) and the ICF package hook.
A57: 7.3 | B57: All other cells are locked by sheet protection (no password - Review > Unprotect Sheet if a change is genuinely needed) so formulas cannot be overwritten by accident.
A58: 7.4 | B58: Re-measure and verify all quantities before pricing or ordering. State any qualification against the item in the Notes column.
A59: 7.5 | B59: The Order guide figures and Schedules A to D are not measured bill items and must not be priced as such. All amounts exclude VAT.

Sheet Summary of Bills
C1: Summary of Bills - section breakdown
C2: ES26-084 | Plot 1 Rivendell Park, Douglas | Mr K & Mrs Burrell - amounts by others, excl. VAT
A4: DISCLAIMER: This information is supplied in good faith for guidance and coordination only. It is not part of the Nudura ICF price and must be checked and verified by the appropriate professional (quantity surveyor, designer, engineer or supplier) before use. Only the Nudura ICF formwork and associated accessories are included in our price. Quantities are measured from the BuildEase quotation model of the Foote McBride planning drawings (C2523 PP 01 001-008, raster, no sections / dimensions / levels - heights scaled from the elevations); no allowance for waste is included unless stated. Quantity columns are the model levels P / BL / FB / L1; the Site total is their sum. Rates and amounts are by others.
A6: Bill | B6: Section | C6: Description | D6: Supply £ | E6: Install £ | F6: Total £
A7: 1 | B7: 1A | C7: External wall finish to the ICF (NRM2 15 / 21 - package EXT; system by others, SPEC TBC) | D7: ='Bill 1 External Finish'!K25 | E7: ='Bill 1 External Finish'!L25 | F7: ='Bill 1 External Finish'!M25
A8: 1 | B8: 1B | C8: Coordination items (supply by others) | D8: ='Bill 1 External Finish'!K26 | E8: ='Bill 1 External Finish'!L26 | F8: ='Bill 1 External Finish'!M26
A9: Bill 1 - External Wall Finish to the ICF (render / cladding - spec TBC) (package EXT) | D9: ='Bill 1 External Finish'!K27 | E9: ='Bill 1 External Finish'!L27 | F9: ='Bill 1 External Finish'!M27
A10: 2 | B10: 2A | C10: Wall linings (NRM2 28 / package DRY) | D10: ='Bill 2 Internal Linings'!K37 | E10: ='Bill 2 Internal Linings'!L37 | F10: ='Bill 2 Internal Linings'!M37
A11: 2 | B11: 2B | C11: Ceilings (NRM2 28 / package DRY) | D11: ='Bill 2 Internal Linings'!K38 | E11: ='Bill 2 Internal Linings'!L38 | F11: ='Bill 2 Internal Linings'!M38
A12: 2 | B12: 2C | C12: Jointing, beads and skim (NRM2 28 / package DRY) | D12: ='Bill 2 Internal Linings'!K39 | E12: ='Bill 2 Internal Linings'!L39 | F12: ='Bill 2 Internal Linings'!M39
A13: Bill 2 - Internal Linings - Walls, Vaulted Ceilings, Tape, Beads & Skim (package DRY) | D13: ='Bill 2 Internal Linings'!K40 | E13: ='Bill 2 Internal Linings'!L40 | F13: ='Bill 2 Internal Linings'!M40
A14: 3 | B14: 3A | C14: Internal doorsets (NRM2 24 / package JOI) | D14: ='Bill 3 Doors'!K27 | E14: ='Bill 3 Doors'!L27 | F14: ='Bill 3 Doors'!M27
A15: 3 | B15: 3B | C15: Ironmongery (NRM2 24 / package JOI) | D15: ='Bill 3 Doors'!K28 | E15: ='Bill 3 Doors'!L28 | F15: ='Bill 3 Doors'!M28
A16: Bill 3 - Internal Doors & Ironmongery (package JOI) | D16: ='Bill 3 Doors'!K29 | E16: ='Bill 3 Doors'!L29 | F16: ='Bill 3 Doors'!M29
A17: 4 | B17: 4A | C17: Skirtings (NRM2 22 / package JOI) | D17: ='Bill 4 Joinery'!K27 | E17: ='Bill 4 Joinery'!L27 | F17: ='Bill 4 Joinery'!M27
A18: 4 | B18: 4B | C18: Architraves (NRM2 22 / package JOI) | D18: ='Bill 4 Joinery'!K28 | E18: ='Bill 4 Joinery'!L28 | F18: ='Bill 4 Joinery'!M28
A19: 4 | B19: 4C | C19: Window boards (NRM2 22 / package JOI) | D19: ='Bill 4 Joinery'!K29 | E19: ='Bill 4 Joinery'!L29 | F19: ='Bill 4 Joinery'!M29
A20: 4 | B20: 4D | C20: Stairs and sundry joinery (NRM2 22 / package JOI) | D20: ='Bill 4 Joinery'!K30 | E20: ='Bill 4 Joinery'!L30 | F20: ='Bill 4 Joinery'!M30
A21: Bill 4 - Joinery - Skirtings, Architraves, Window Boards & Stair (package JOI) | D21: ='Bill 4 Joinery'!K31 | E21: ='Bill 4 Joinery'!L31 | F21: ='Bill 4 Joinery'!M31
A22: 5 | B22: 5A | C22: Timber stud partitions, non-loadbearing - framing (NRM2 16 / package JOI) | D22: ='Bill 5 Partitions'!K39 | E22: ='Bill 5 Partitions'!L39 | F22: ='Bill 5 Partitions'!M39
A23: 5 | B23: 5B | C23: Partition timber - supply (NRM2 16 / package JOI) | D23: ='Bill 5 Partitions'!K40 | E23: ='Bill 5 Partitions'!L40 | F23: ='Bill 5 Partitions'!M40
A24: 5 | B24: 5C | C24: Forming door openings in partitions (NRM2 16 / package JOI) | D24: ='Bill 5 Partitions'!K41 | E24: ='Bill 5 Partitions'!L41 | F24: ='Bill 5 Partitions'!M41
A25: 5 | B25: 5D | C25: Head restraint, pattresses, acoustic and fixings (NRM2 16 / package JOI) | D25: ='Bill 5 Partitions'!K42 | E25: ='Bill 5 Partitions'!L42 | F25: ='Bill 5 Partitions'!M42
A26: Bill 5 - Timber Stud Partitions (TLSTF) - Framing, Openings, Head Restraint & Fixings (package JOI) | D26: ='Bill 5 Partitions'!K43 | E26: ='Bill 5 Partitions'!L43 | F26: ='Bill 5 Partitions'!M43
A27: 6 | B27: 6A | C27: RC base, raft and slabs (NRM2 11 - package RCF; by others - engineer; coordination quantities) | D27: ='Bill 6 Slabs'!K30 | E27: ='Bill 6 Slabs'!L30 | F27: ='Bill 6 Slabs'!M30
A28: 6 | B28: 6B | C28: Floor build-ups (NRM2 11 / 28 - package FLR; by others) | D28: ='Bill 6 Slabs'!K31 | E28: ='Bill 6 Slabs'!L31 | F28: ='Bill 6 Slabs'!M31
A29: 6 | B29: 6C | C29: Coordination | D29: ='Bill 6 Slabs'!K32 | E29: ='Bill 6 Slabs'!L32 | F29: ='Bill 6 Slabs'!M32
A30: Bill 6 - Substructure & Slabs - Pool Base, Raft, GF Slab, Floor Build-ups (coordination) (package RCF / FLR) | D30: ='Bill 6 Slabs'!K33 | E30: ='Bill 6 Slabs'!L33 | F30: ='Bill 6 Slabs'!M33
A31: 7 | B31: 7A | C31: Roof structure - vaulted cut roof (NRM2 16 - package RFS; roof designer / engineer) | D31: ='Bill 7 Roof'!K46 | E31: ='Bill 7 Roof'!L46 | F31: ='Bill 7 Roof'!M46
A32: 7 | B32: 7B | C32: Roof covering, eaves, verges and rainwater (NRM2 18 / 33 - package RFC) | D32: ='Bill 7 Roof'!K47 | E32: ='Bill 7 Roof'!L47 | F32: ='Bill 7 Roof'!M47
A33: 7 | B33: 7C | C33: Roof insulation, VCL and soffits (NRM2 18 / 28 - package RFC) | D33: ='Bill 7 Roof'!K48 | E33: ='Bill 7 Roof'!L48 | F33: ='Bill 7 Roof'!M48
A34: Bill 7 - Vaulted Roof - Structure, Covering, Rainwater & Insulation (package RFS / RFC) | D34: ='Bill 7 Roof'!K49 | E34: ='Bill 7 Roof'!L49 | F34: ='Bill 7 Roof'!M49
A35: 8 | B35: 8A | C35: Windows - UPVC casements (NRM2 25 - package WIN; window supplier) | D35: ='Bill 8 Glazing'!K39 | E35: ='Bill 8 Glazing'!L39 | F35: ='Bill 8 Glazing'!M39
A36: 8 | B36: 8B | C36: External doors (NRM2 25 - package WIN) | D36: ='Bill 8 Glazing'!K40 | E36: ='Bill 8 Glazing'!L40 | F36: ='Bill 8 Glazing'!M40
A37: 8 | B37: 8C | C37: Glazed screens - stair (NRM2 25 - package WIN) | D37: ='Bill 8 Glazing'!K41 | E37: ='Bill 8 Glazing'!L41 | F37: ='Bill 8 Glazing'!M41
A38: 8 | B38: 8D | C38: Raked feature glazing screens to the vaulted roof / glazed gables (NRM2 25 - package GLZ; GLAZING SPECIALIST) | D38: ='Bill 8 Glazing'!K42 | E38: ='Bill 8 Glazing'!L42 | F38: ='Bill 8 Glazing'!M42
A39: 8 | B39: 8E | C39: Guarding, garage door and items not modelled (PROVISIONAL) | D39: ='Bill 8 Glazing'!K43 | E39: ='Bill 8 Glazing'!L43 | F39: ='Bill 8 Glazing'!M43
A40: Bill 8 - Glazing, External Doors, Raked Feature Screens & Garage Door (package WIN / GLZ) | D40: ='Bill 8 Glazing'!K44 | E40: ='Bill 8 Glazing'!L44 | F40: ='Bill 8 Glazing'!M44
A41: 9 | B41: 9A | C41: BS 8102:2022 waterproofing - PROVISIONAL (NRM2 17 - package WPF; SPECIALIST WATERPROOFING DESIGNER) | D41: ='Bill 9 Waterproofing Pool'!K29 | E41: ='Bill 9 Waterproofing Pool'!L29 | F41: ='Bill 9 Waterproofing Pool'!M29
A42: 9 | B42: 9B | C42: ICF pool tank (NRM2 - package POOL; POOL SPECIALIST - PROVISIONAL) | D42: ='Bill 9 Waterproofing Pool'!K30 | E42: ='Bill 9 Waterproofing Pool'!L30 | F42: ='Bill 9 Waterproofing Pool'!M30
A43: Bill 9 - Basement Waterproofing (BS 8102) & ICF Pool Tank - PROVISIONAL (package WPF / POOL) | D43: ='Bill 9 Waterproofing Pool'!K31 | E43: ='Bill 9 Waterproofing Pool'!L31 | F43: ='Bill 9 Waterproofing Pool'!M31
A44: TOTAL - finishes / ancillary trades, net (agrees with the Cover overview) | D44: =D9+D13+D16+D21+D26+D30+D34+D40+D43 | E44: =E9+E13+E16+E21+E26+E30+E34+E40+E43 | F44: =F9+F13+F16+F21+F26+F30+F34+F40+F43
A46: Schedules A to D are reference schedules and are not priced. Preliminaries, overheads & profit, contingency and the ICF package (BuildEase BOQ Builder) are applied on the Cover.

Sheet Bill 1 External Finish
C1: Bill 1 - External Wall Finish to the ICF (render / cladding - spec TBC)
C2: External finish to the ICF EPS faces of the GF walls and the exposed basement / footing faces, with beads, trims and coordination items (system by others, spec TBC). [NRM2 15 / 21 / package EXT]
A4: DISCLAIMER: This information is supplied in good faith for guidance and coordination only. It is not part of the Nudura ICF price and must be checked and verified by the appropriate professional (quantity surveyor, designer, engineer or supplier) before use. Only the Nudura ICF formwork and associated accessories are included in our price. Quantities are measured from the BuildEase quotation model of the Foote McBride planning drawings (C2523 PP 01 001-008, raster, no sections / dimensions / levels - heights scaled from the elevations); no allowance for waste is included unless stated. Quantity columns are the model levels P / BL / FB / L1; the Site total is their sum. Rates and amounts are by others.
A6: Ref | B6: Description | C6: Unit | D6: P pool tank | E6: BL basement | F6: FB master footing | G6: L1 ground floor | H6: Site total qty | I6: Supply rate £ | J6: Install rate £ | K6: Supply £ | L6: Install £ | M6: Line total £ | N6: Notes
B7: One building - quantity per level (Site total = sum of the levels) | D7: 1 | E7: 1 | F7: 1 | G7: 1 | H7: =SUM(D7:G7) | N7: Levels: P = pool tank: 3 courses 10in Std, -5,029 to -3,658 (on the pool base); BL = basement: 8 courses 10in Std, FFL -3,300 - garage, laundry, stores, pool hall; FB = master-suite footing: 2 courses 6in XR35, -914 to 0 (no basement under it); L1 = ground floor: 14 courses 6in XR35 incl. the raked gables, vaulted ceilings
A8: 1A External wall finish to the ICF (NRM2 15 / 21 - package EXT; system by others, SPEC TBC)
B9: The Foote McBride elevations show the walls plain (no hatch / material key on the renders read) and the roof hatched as slate / tile: the external wall finish is measured generically as "external finish to the ICF EPS face - render or cladding system, spec TBC (by others)". Areas are the modelled ICF outer EPS faces (Report Tool component export, openings and glazing gaps already net): GF from FFL to the eaves plate (2,286) and up the raked gables; below FFL the exposed basement / footing faces down to finished ground, scaled off the elevation renders (+-150 mm; the faces and depths are listed in Schedule A). Where the ground is at DPC (rear, terrace) a 150 mm band is included.
A10: 1A.1 | B10: External finish to the ICF EPS face, GF walls incl. the raked gables (FFL to the plate / gable rake), net of openings: render or cladding system, spec TBC (base coat + mesh + finish, or battens + cladding) - by others | C10: m2 | G10: 161.985 | H10: =SUMPRODUCT($D$7:$G$7,D10:G10) | K10: =N(H10)*N(I10) | L10: =N(H10)*N(J10) | M10: =K10+L10 | N10: Order guide +10% = 178.2; GF outer faces 165.9 less the hall stub 3.9 (interior)
A11: 1A.2 | B11: Ditto, exposed basement / master-suite footing faces below FFL to finished ground (garage front + apron, west, east, wing front; DPC band at the rear), net of the basement openings - PROVISIONAL | C11: m2 | E11: 72.759 | F11: 4.611 | H11: =SUMPRODUCT($D$7:$G$7,D11:G11) | K11: =N(H11)*N(I11) | L11: =N(H11)*N(J11) | M11: =K11+L11 | N11: Ground lines scaled off the elevations (Schedule A); BL gross 90.1 less openings 17.4. Re-measure on the finished levels
A12: 1A.3 | B12: Reveal returns at windows / doors in the ICF (head + jambs; frames tight to the back of the outer EPS): girth 102 GF / 67 basement | C12: m2 | E12: 1.477 | G12: 5.231 | H12: =SUMPRODUCT($D$7:$G$7,D12:G12) | K12: =N(H12)*N(I12) | L12: =N(H12)*N(J12) | M12: =K12+L12 | N12: Order guide +10% = 7.4; GF windows are floor-length (no sill reveal)
A13: 1A.4 | B13: Returns at the ICF wall ends beside the glazed screens and glazing gaps (jamb returns ~102 girth), incl. stop / edge bead | C13: m | E13: 11.172 | G13: 30.835 | H13: =SUMPRODUCT($D$7:$G$7,D13:G13) | K13: =N(H13)*N(I13) | L13: =N(H13)*N(J13) | M13: =K13+L13 | N13: Screens G01, G02 / G02R, G03a / b, G05, BL-G04 (Schedule B); G03a / G03b meet at a glazed corner
A14: 1A.5 | B14: External corner bead / angle to the vertical external corners (GF to the plate / gable; basement / footing corners to ground) | C14: m | E14: 6.664 | F14: 0.365 | G14: 16.916 | H14: =SUMPRODUCT($D$7:$G$7,D14:G14) | K14: =N(H14)*N(I14) | L14: =N(H14)*N(J14) | M14: =K14+L14 | N14: Order guide +10% = 26.3
A15: 1A.6 | B15: Base / starter track (bellcast bead, drip) at finished ground or DPC level, incl. below-ground termination of the finish | C15: m | E15: 45.786 | F15: 14.811 | H15: =SUMPRODUCT($D$7:$G$7,D15:G15) | K15: =N(H15)*N(I15) | L15: =N(H15)*N(J15) | M15: =K15+L15 | N15: Order guide +10% = 66.7; door thresholds deducted (garage door, laundry door)
A16: 1A.7 | B16: Head stop / closure bead at the eaves soffit (eaves walls) and along the gable verge rakes | C16: m | G16: 66.684 | H16: =SUMPRODUCT($D$7:$G$7,D16:G16) | K16: =N(H16)*N(I16) | L16: =N(H16)*N(J16) | M16: =K16+L16 | N16: Eaves walls 38.8 + gable rakes 27.9; Order guide +10% = 73.4
A17: 1A.8 | B17: Movement / sealant joint between the finish and the window, door and screen frames (backer rod + low-modulus sealant) | C17: m | E17: 33.283 | G17: 82.22 | H17: =SUMPRODUCT($D$7:$G$7,D17:G17) | K17: =N(H17)*N(I17) | L17: =N(H17)*N(J17) | M17: =K17+L17 | N17: Order guide +10% = 127.1
A18: 1B Coordination items (supply by others)
A19: 1B.1 | B19: External cills / thresholds at the structural openings (GF: floor-length windows + bi-folds = thresholds; basement: pool windows + laundry door) | C19: m | E19: 9.675 | G19: 14.035 | H19: =SUMPRODUCT($D$7:$G$7,D19:G19) | K19: =N(H19)*N(I19) | L19: =N(H19)*N(J19) | M19: =K19+L19 | N19: By the window / door supplier - coordination only
A20: 1B.2 | B20: Chimney / stove flue on the lounge west wall (drawn on the elevations, NOT modelled): finish, flashings and flue by others | C20: item | K20: =IF(ISNUMBER(H20),H20,1)*N(I20) | L20: =IF(ISNUMBER(H20),H20,1)*N(J20) | M20: =K20+L20 | N20: Lump sum - the rate entered is the amount. Not measured - chimney not in the model
A21: 1B.3 | B21: Basement rear retaining wall running on 1.5 m past the house (x 15,076-16,744): exposed face finish / backfill by the groundworker | C21: item | K21: =IF(ISNUMBER(H21),H21,1)*N(I21) | L21: =IF(ISNUMBER(H21),H21,1)*N(J21) | M21: =K21+L21 | N21: Lump sum - the rate entered is the amount. Exposure not shown on the elevations - not measured
A23: PACKAGE SUMMARY - Bill 1 External Wall Finish to the ICF (render / cladding - spec TBC) (package EXT; amounts by others, excl. VAT)
A24: Section | B24: Description | K24: Supply £ | L24: Install £ | M24: Total £
A25: 1A | B25: External wall finish to the ICF (NRM2 15 / 21 - package EXT; system by others, SPEC TBC) | K25: =SUM(K9:K17) | L25: =SUM(L9:L17) | M25: =SUM(M9:M17)
A26: 1B | B26: Coordination items (supply by others) | K26: =SUM(K19:K21) | L26: =SUM(L19:L21) | M26: =SUM(M19:M21)
A27: PACKAGE TOTAL - Bill 1, carried to the Cover overview | K27: =SUM(K25:K26) | L27: =SUM(L25:L26) | M27: =SUM(M25:M26)
A28: Pale-yellow cells are the only inputs (Supply rate, Install rate). Amounts, subtotals and totals are formulas; the sheet is protected without a password (Review > Unprotect Sheet). Amounts exclude VAT and are NOT part of the Nudura ICF price.

Sheet Bill 2 Internal Linings
C1: Bill 2 - Internal Linings - Walls, Vaulted Ceilings, Tape, Beads & Skim
C2: Dry linings to the ICF inner faces (thermal barrier to the EPS), TLSTF partitions, reveals, basement ceilings and the GF vaulted ceilings (on the slope). [NRM2 28 / package DRY]
A4: DISCLAIMER: This information is supplied in good faith for guidance and coordination only. It is not part of the Nudura ICF price and must be checked and verified by the appropriate professional (quantity surveyor, designer, engineer or supplier) before use. Only the Nudura ICF formwork and associated accessories are included in our price. Quantities are measured from the BuildEase quotation model of the Foote McBride planning drawings (C2523 PP 01 001-008, raster, no sections / dimensions / levels - heights scaled from the elevations); no allowance for waste is included unless stated. Quantity columns are the model levels P / BL / FB / L1; the Site total is their sum. Rates and amounts are by others.
A6: Ref | B6: Description | C6: Unit | D6: P pool tank | E6: BL basement | F6: FB master footing | G6: L1 ground floor | H6: Site total qty | I6: Supply rate £ | J6: Install rate £ | K6: Supply £ | L6: Install £ | M6: Line total £ | N6: Notes
B7: One building - quantity per level (Site total = sum of the levels) | D7: 1 | E7: 1 | F7: 1 | G7: 1 | H7: =SUM(D7:G7) | N7: Levels: P = pool tank: 3 courses 10in Std, -5,029 to -3,658 (on the pool base); BL = basement: 8 courses 10in Std, FFL -3,300 - garage, laundry, stores, pool hall; FB = master-suite footing: 2 courses 6in XR35, -914 to 0 (no basement under it); L1 = ground floor: 14 courses 6in XR35 incl. the raked gables, vaulted ceilings
A8: 2A Wall linings (NRM2 28 / package DRY)
B9: Measured on the modelled ICF inner EPS faces (component export, openings net). Basement: FFL -3,300 to the GF slab soffit -325 (2,975 clear); GF: FFL to the vaulted ceiling - the gable triangles and the eaves walls up to the rafters are lined (vaulted rooms). TLSTF partitions both faces, door gaps deducted (2,100 high); GF partitions are raked to the vault (200.9 m2 one face). EPS faces must be covered by a thermal barrier (min. 12.5 mm board, mechanically fixed to the ICF webs) whatever the finish. Basement linings follow the BS 8102 design (Bill 9): with a Type C cavity drain the board goes on battens inside the membrane - PROVISIONAL build-up.
A10: 2A.1 | B10: Basement ICF inner face - stair / hall, stores, laundry, plant (FFL -3,300 to -325): 12.5 mm board on battens / inside the cavity drain membrane (BS 8102 - PROVISIONAL) | C10: m2 | E10: 84.738 | H10: =SUMPRODUCT($D$7:$G$7,D10:G10) | K10: =N(H10)*N(I10) | L10: =N(H10)*N(J10) | M10: =K10+L10 | N10: incl. both faces of the internal ICF store nib + stub (8.8); Order guide +10% = 93.2
A11: 2A.2 | B11: Garage ICF inner face (integral garage): 12.5 mm board mechanically fixed (EPS thermal barrier); fire-resisting lining where the warrant requires | C11: m2 | E11: 32.593 | H11: =SUMPRODUCT($D$7:$G$7,D11:G11) | K11: =N(H11)*N(I11) | L11: =N(H11)*N(J11) | M11: =K11+L11 | N11: Order guide +10% = 35.9
A12: 2A.3 | B12: Pool hall walls (ICF inner face around the pool): moisture-resistant / cement-based board + tanking + tiling by the pool specialist - PROVISIONAL | C12: m2 | E12: 41.364 | H12: =SUMPRODUCT($D$7:$G$7,D12:G12) | K12: =N(H12)*N(I12) | L12: =N(H12)*N(J12) | M12: =K12+L12 | N12: Pool specialist; Order guide +10% = 45.5
A13: 2A.4 | B13: GF ICF inner face incl. the gable triangles up to the vault + the hall face of the wing stub: 12.5 mm wallboard on dabs + mechanical fixings to the ICF webs (MR board in the ensuites / cloaks) | C13: m2 | G13: 161.85 | H13: =SUMPRODUCT($D$7:$G$7,D13:G13) | K13: =N(H13)*N(I13) | L13: =N(H13)*N(J13) | M13: =K13+L13 | N13: inner faces 157.9 + stub 3.9; Order guide +10% = 178.0
A14: 2A.5 | B14: Basement TLSTF partitions - both faces (garage faces in 2A.6): 15 mm board on 38 x 89 studs; MR in the laundry | C14: m2 | E14: 128.972 | H14: =SUMPRODUCT($D$7:$G$7,D14:G14) | K14: =N(H14)*N(I14) | L14: =N(H14)*N(J14) | M14: =K14+L14 | N14: Order guide +10% = 141.9
A15: 2A.6 | B15: Garage faces of the garage / dwelling partitions BF-P03 + BF-P04: fire-resisting board (e.g. 2 x 15 mm FR) per the building warrant (Section 2 Fire) - PROVISIONAL | C15: m2 | E15: 36.525 | H15: =SUMPRODUCT($D$7:$G$7,D15:G15) | K15: =N(H15)*N(I15) | L15: =N(H15)*N(J15) | M15: =K15+L15 | N15: Separation garage / dwelling; Order guide +10% = 40.2
A16: 2A.7 | B16: GF TLSTF partitions - both faces, raked heads to the vaulted ceiling: 15 mm board on 38 x 89 studs; MR in the ensuites / cloaks | C16: m2 | G16: 379.369 | H16: =SUMPRODUCT($D$7:$G$7,D16:G16) | K16: =N(H16)*N(I16) | L16: =N(H16)*N(J16) | M16: =K16+L16 | N16: Tall raked walls - board to 5.9 m; Order guide +10% = 417.3
A17: 2A.8 | B17: Internal reveals to windows / doors in the ICF, jambs and heads, 211 deep GF / 278 basement: board / bonding + skim | C17: m2 | E17: 6.148 | G17: 10.858 | H17: =SUMPRODUCT($D$7:$G$7,D17:G17) | K17: =N(H17)*N(I17) | L17: =N(H17)*N(J17) | M17: =K17+L17 | N17: Order guide +10% = 18.7
A18: 2A.9 | B18: Internal returns at the ICF wall ends beside the glazed screens (same depth as the reveals) | C18: m2 | E18: 3.106 | G18: 6.515 | H18: =SUMPRODUCT($D$7:$G$7,D18:G18) | K18: =N(H18)*N(I18) | L18: =N(H18)*N(J18) | M18: =K18+L18 | N18: Order guide +10% = 10.6
A19: 2B Ceilings (NRM2 28 / package DRY)
B20: Basement: the soffit of the GF suspended slab (-325), net plan areas (Schedule A). GF: VAULTED throughout - plasterboard on the rafter soffits, MEASURED ON THE SLOPE (45 deg: plan 199.8 m2 x 1.414); the insulation / VCL build-up is in Bill 7C.
A21: 2B.1 | B21: Basement ceilings (stair / hall, stores, laundry) under the GF slab: MF ceiling grid + 12.5 mm board, or tape-and-fill direct to the slab | C21: m2 | E21: 87.539 | H21: =SUMPRODUCT($D$7:$G$7,D21:G21) | K21: =N(H21)*N(I21) | L21: =N(H21)*N(J21) | M21: =K21+L21 | N21: Order guide +10% = 96.3
A22: 2B.2 | B22: Integral garage ceiling under the dwelling: fire-resisting ceiling (e.g. 2 x 15 mm FR board on MF) per the warrant - PROVISIONAL | C22: m2 | E22: 49.049 | H22: =SUMPRODUCT($D$7:$G$7,D22:G22) | K22: =N(H22)*N(I22) | L22: =N(H22)*N(J22) | M22: =K22+L22 | N22: Garage 7.0 x 7.0
A23: 2B.3 | B23: Pool hall ceiling: moisture-resistant board + VCL (pool hall environment) - by / to the pool specialist, PROVISIONAL | C23: m2 | E23: 43.401 | H23: =SUMPRODUCT($D$7:$G$7,D23:G23) | K23: =N(H23)*N(I23) | L23: =N(H23)*N(J23) | M23: =K23+L23 | N23: Pool specialist
A24: 2B.4 | B24: GF vaulted ceilings: 12.5 mm board (or insulated board) on the rafter soffits, measured on the 45 deg slope | C24: m2 | G24: 282.549 | H24: =SUMPRODUCT($D$7:$G$7,D24:G24) | K24: =N(H24)*N(I24) | L24: =N(H24)*N(J24) | M24: =K24+L24 | N24: Order guide +10% = 310.8; plan 199.8 m2
A25: 2B.5 | B25: Ridge beam linings / boxings where the beams drop below the vault: Roof L 120 x 400 GL24h (20.7 m), Roof R 140 x 800 GL24h (12.3 m) - or exposed feature finish (client) | C25: m | G25: 32.745 | H25: =SUMPRODUCT($D$7:$G$7,D25:G25) | K25: =N(H25)*N(I25) | L25: =N(H25)*N(J25) | M25: =K25+L25 | N25: Girth to suit; glulam may be left exposed
A26: 2C Jointing, beads and skim (NRM2 28 / package DRY)
A27: 2C.1 | B27: Scrim tape, board joints (walls / 1.2 m; ceilings / 1.2 + 2.4 m) | C27: m | E27: 414.137 | G27: 818.681 | H27: =SUMPRODUCT($D$7:$G$7,D27:G27) | K27: =N(H27)*N(I27) | L27: =N(H27)*N(J27) | M27: =K27+L27 | N27: Order guide +10% = 1,356.1
A28: 2C.2 | B28: Scrim tape, internal angles wall to wall (4 per partition + ICF internal corners) | C28: m | E28: 113.05 | G28: 401.905 | H28: =SUMPRODUCT($D$7:$G$7,D28:G28) | K28: =N(H28)*N(I28) | L28: =N(H28)*N(J28) | M28: =K28+L28 | N28: Estimate - no room model; Order guide +10% = 566.5
A29: 2C.3 | B29: Scrim tape, wall to ceiling angles (eaves / gable heads + partition heads both sides) | C29: m | E29: 106.155 | G29: 171.441 | H29: =SUMPRODUCT($D$7:$G$7,D29:G29) | K29: =N(H29)*N(I29) | L29: =N(H29)*N(J29) | M29: =K29+L29 | N29: Estimate; Order guide +10% = 305.4
A30: 2C.4 | B30: Angle bead, window / door reveals and screen-end returns | C30: m | E30: 33.283 | G30: 82.22 | H30: =SUMPRODUCT($D$7:$G$7,D30:G30) | K30: =N(H30)*N(I30) | L30: =N(H30)*N(J30) | M30: =K30+L30 | N30: Order guide +10% = 127.1
A31: 2C.5 | B31: Skim coat, 2-3 mm, to all net wall, reveal and ceiling board faces (pool hall excluded - specialist) | C31: m2 | E31: 428.67 | G31: 841.142 | H31: =SUMPRODUCT($D$7:$G$7,D31:G31) | K31: =N(H31)*N(I31) | L31: =N(H31)*N(J31) | M31: =K31+L31 | N31: Face layer only
A32: 2D Ordering guide (not a measured item)
A33: 2D.1 | B33: Plasterboard to purchase, all types, before waste (excl. pool hall) | C33: m2 | E33: 428.67 | G33: 841.142 | H33: =SUMPRODUCT($D$7:$G$7,D33:G33) | M33: not priced | N33: Order guide +10% = 1,396.8 (guide only)
A35: PACKAGE SUMMARY - Bill 2 Internal Linings - Walls, Vaulted Ceilings, Tape, Beads & Skim (package DRY; amounts by others, excl. VAT)
A36: Section | B36: Description | K36: Supply £ | L36: Install £ | M36: Total £
A37: 2A | B37: Wall linings (NRM2 28 / package DRY) | K37: =SUM(K9:K18) | L37: =SUM(L9:L18) | M37: =SUM(M9:M18)
A38: 2B | B38: Ceilings (NRM2 28 / package DRY) | K38: =SUM(K20:K25) | L38: =SUM(L20:L25) | M38: =SUM(M20:M25)
A39: 2C | B39: Jointing, beads and skim (NRM2 28 / package DRY) | K39: =SUM(K27:K31) | L39: =SUM(L27:L31) | M39: =SUM(M27:M31)
A40: PACKAGE TOTAL - Bill 2, carried to the Cover overview | K40: =SUM(K37:K39) | L40: =SUM(L37:L39) | M40: =SUM(M37:M39)
A41: Pale-yellow cells are the only inputs (Supply rate, Install rate). Amounts, subtotals and totals are formulas; the sheet is protected without a password (Review > Unprotect Sheet). Amounts exclude VAT and are NOT part of the Nudura ICF price.

Sheet Bill 3 Doors
C1: Bill 3 - Internal Doors & Ironmongery
C2: Internal doorsets and ironmongery per level from the TLSTF door openings (13 nr), incl. the fire-resisting garage doors. [NRM2 24 / package JOI]
A4: DISCLAIMER: This information is supplied in good faith for guidance and coordination only. It is not part of the Nudura ICF price and must be checked and verified by the appropriate professional (quantity surveyor, designer, engineer or supplier) before use. Only the Nudura ICF formwork and associated accessories are included in our price. Quantities are measured from the BuildEase quotation model of the Foote McBride planning drawings (C2523 PP 01 001-008, raster, no sections / dimensions / levels - heights scaled from the elevations); no allowance for waste is included unless stated. Quantity columns are the model levels P / BL / FB / L1; the Site total is their sum. Rates and amounts are by others.
A6: Ref | B6: Description | C6: Unit | D6: P pool tank | E6: BL basement | F6: FB master footing | G6: L1 ground floor | H6: Site total qty | I6: Supply rate £ | J6: Install rate £ | K6: Supply £ | L6: Install £ | M6: Line total £ | N6: Notes
B7: One building - quantity per level (Site total = sum of the levels) | D7: 1 | E7: 1 | F7: 1 | G7: 1 | H7: =SUM(D7:G7) | N7: Levels: P = pool tank: 3 courses 10in Std, -5,029 to -3,658 (on the pool base); BL = basement: 8 courses 10in Std, FFL -3,300 - garage, laundry, stores, pool hall; FB = master-suite footing: 2 courses 6in XR35, -914 to 0 (no basement under it); L1 = ground floor: 14 courses 6in XR35 incl. the raked gables, vaulted ceilings
A8: 3A Internal doorsets (NRM2 24 / package JOI)
B9: From the TLSTF door report (13 openings: basement 6, GF 7). Leaf = the largest standard 1,981-high leaf that fits the opening less 68 (2 x 32 lining + clearances): 830-855 -> 762; 800 -> 711; 762 -> 686; 680 -> 610. Wet rooms from the pattress reports (ensuites, cloaks, laundry). SCOTLAND: Standard 4.2 - the architect to check the clear opening widths (775 mm effective to apartments, the kitchen and the accessible sanitary room); the 680 / 762 openings are likely to need widening. Doors between the integral garage and the dwelling: fire-resisting and self-closing per the building warrant (Section 2 Fire).
A10: 3A.1 | B10: Internal doorset, 762 x 1,981 leaf, 32 x 125 lining set, stops, ensuite / cloaks (privacy) | C10: nr | G10: 1 | H10: =SUMPRODUCT($D$7:$G$7,D10:G10) | K10: =N(H10)*N(I10) | L10: =N(H10)*N(J10) | M10: =K10+L10 | N10: GF-D03 (850)
A11: 3A.2 | B11: Internal doorset, 610 x 1,981 leaf, 32 x 125 lining set, stops, ensuite / cloaks (privacy) | C11: nr | G11: 2 | H11: =SUMPRODUCT($D$7:$G$7,D11:G11) | K11: =N(H11)*N(I11) | L11: =N(H11)*N(J11) | M11: =K11+L11 | N11: GF-D05 (680), GF-D07 (680)
A12: 3A.3 | B12: FIRE-RESISTING self-closing doorset, 762 x 1,981 leaf, intumescent + smoke seals, lining to suit the 119 partition, garage to dwelling | C12: nr | E12: 1 | H12: =SUMPRODUCT($D$7:$G$7,D12:G12) | K12: =N(H12)*N(I12) | L12: =N(H12)*N(J12) | M12: =K12+L12 | N12: BF-D05 (850); rating per the warrant
A13: 3A.4 | B13: FIRE-RESISTING self-closing doorset, 711 x 1,981 leaf, intumescent + smoke seals, lining to suit the 119 partition, garage to dwelling | C13: nr | E13: 1 | H13: =SUMPRODUCT($D$7:$G$7,D13:G13) | K13: =N(H13)*N(I13) | L13: =N(H13)*N(J13) | M13: =K13+L13 | N13: BF-D02 (800); rating per the warrant
A14: 3A.5 | B14: Internal doorset, 762 x 1,981 leaf, 32 x 125 lining set, stops, habitable rooms / stores / laundry | C14: nr | E14: 4 | G14: 2 | H14: =SUMPRODUCT($D$7:$G$7,D14:G14) | K14: =N(H14)*N(I14) | L14: =N(H14)*N(J14) | M14: =K14+L14 | N14: BF-D01 (830), BF-D03 (850), BF-D04 (846), BF-D06 (850), GF-D01 (855), GF-D02 (850)
A15: 3A.6 | B15: Internal doorset, 686 x 1,981 leaf, 32 x 125 lining set, stops, habitable rooms / stores / laundry | C15: nr | G15: 1 | H15: =SUMPRODUCT($D$7:$G$7,D15:G15) | K15: =N(H15)*N(I15) | L15: =N(H15)*N(J15) | M15: =K15+L15 | N15: GF-D06 (762)
A16: 3A.7 | B16: Internal doorset, 610 x 1,981 leaf, 32 x 125 lining set, stops, habitable rooms / stores / laundry | C16: nr | G16: 1 | H16: =SUMPRODUCT($D$7:$G$7,D16:G16) | K16: =N(H16)*N(I16) | L16: =N(H16)*N(J16) | M16: =K16+L16 | N16: GF-D04 (680)
A17: 3B Ironmongery (NRM2 24 / package JOI)
A18: 3B.1 | B18: Butt hinges, 100 mm, pairs (1.5 pair per leaf; fire-rated on the garage doors) | C18: pr | E18: 9 | G18: 10.5 | H18: =SUMPRODUCT($D$7:$G$7,D18:G18) | K18: =N(H18)*N(I18) | L18: =N(H18)*N(J18) | M18: =K18+L18 | N18: 1.5 pr per leaf
A19: 3B.2 | B19: Standard sets: tubular latch, lever pair on roses | C19: set | E19: 4 | G19: 4 | H19: =SUMPRODUCT($D$7:$G$7,D19:G19) | K19: =N(H19)*N(I19) | L19: =N(H19)*N(J19) | M19: =K19+L19
A20: 3B.3 | B20: Bathroom / WC sets: privacy lock, thumb-turn with emergency release, lever pair | C20: set | G20: 3 | H20: =SUMPRODUCT($D$7:$G$7,D20:G20) | K20: =N(H20)*N(I20) | L20: =N(H20)*N(J20) | M20: =K20+L20 | N20: Ensuites / cloaks
A21: 3B.4 | B21: Fire door sets (garage doors): latch, lever pair, overhead closer, "Fire door keep shut" signs | C21: set | E21: 2 | H21: =SUMPRODUCT($D$7:$G$7,D21:G21) | K21: =N(H21)*N(I21) | L21: =N(H21)*N(J21) | M21: =K21+L21 | N21: Per the warrant
A22: 3B.5 | B22: Door stops, floor or skirting mounted | C22: nr | E22: 6 | G22: 7 | H22: =SUMPRODUCT($D$7:$G$7,D22:G22) | K22: =N(H22)*N(I22) | L22: =N(H22)*N(J22) | M22: =K22+L22 | N22: One per leaf
B23: External doorsets, bi-folds, screens and the garage door are in Bill 8 (glazing / external doors).
A25: PACKAGE SUMMARY - Bill 3 Internal Doors & Ironmongery (package JOI; amounts by others, excl. VAT)
A26: Section | B26: Description | K26: Supply £ | L26: Install £ | M26: Total £
A27: 3A | B27: Internal doorsets (NRM2 24 / package JOI) | K27: =SUM(K9:K16) | L27: =SUM(L9:L16) | M27: =SUM(M9:M16)
A28: 3B | B28: Ironmongery (NRM2 24 / package JOI) | K28: =SUM(K18:K23) | L28: =SUM(L18:L23) | M28: =SUM(M18:M23)
A29: PACKAGE TOTAL - Bill 3, carried to the Cover overview | K29: =SUM(K27:K28) | L29: =SUM(L27:L28) | M29: =SUM(M27:M28)
A30: Pale-yellow cells are the only inputs (Supply rate, Install rate). Amounts, subtotals and totals are formulas; the sheet is protected without a password (Review > Unprotect Sheet). Amounts exclude VAT and are NOT part of the Nudura ICF price.

Sheet Bill 4 Joinery
C1: Bill 4 - Joinery - Skirtings, Architraves, Window Boards & Stair
C2: Second-fix joinery measured per level from the model wall faces and openings; the basement stair is a provisional item (not modelled). [NRM2 22 / package JOI]
A4: DISCLAIMER: This information is supplied in good faith for guidance and coordination only. It is not part of the Nudura ICF price and must be checked and verified by the appropriate professional (quantity surveyor, designer, engineer or supplier) before use. Only the Nudura ICF formwork and associated accessories are included in our price. Quantities are measured from the BuildEase quotation model of the Foote McBride planning drawings (C2523 PP 01 001-008, raster, no sections / dimensions / levels - heights scaled from the elevations); no allowance for waste is included unless stated. Quantity columns are the model levels P / BL / FB / L1; the Site total is their sum. Rates and amounts are by others.
A6: Ref | B6: Description | C6: Unit | D6: P pool tank | E6: BL basement | F6: FB master footing | G6: L1 ground floor | H6: Site total qty | I6: Supply rate £ | J6: Install rate £ | K6: Supply £ | L6: Install £ | M6: Line total £ | N6: Notes
B7: One building - quantity per level (Site total = sum of the levels) | D7: 1 | E7: 1 | F7: 1 | G7: 1 | H7: =SUM(D7:G7) | N7: Levels: P = pool tank: 3 courses 10in Std, -5,029 to -3,658 (on the pool base); BL = basement: 8 courses 10in Std, FFL -3,300 - garage, laundry, stores, pool hall; FB = master-suite footing: 2 courses 6in XR35, -914 to 0 (no basement under it); L1 = ground floor: 14 courses 6in XR35 incl. the raked gables, vaulted ceilings
A8: 4A Skirtings (NRM2 22 / package JOI)
B9: No room model: every lined wall face at floor level (ICF inner faces from the bottom course of the component export - floor-length GF windows and the bi-fold already net; partitions both faces) less internal door gaps (both faces) and the laundry door. Excluded: the garage and the pool hall (tiled - pool specialist). 18 x 119 MDF, profile by the client.
A10: 4A.1 | B10: Skirting 18 x 119 MDF, primed, fixed to the linings | C10: m | E10: 68.915 | G10: 119.617 | H10: =SUMPRODUCT($D$7:$G$7,D10:G10) | K10: =N(H10)*N(I10) | L10: =N(H10)*N(J10) | M10: =K10+L10 | N10: Order guide +10% = 207.4
A11: 4B Architraves (NRM2 22 / package JOI)
B12: Per face = 2 legs x 2150 + (opening + 2 x 70). Internal doors both faces; the bi-folds and the laundry door inside face only; GF windows are floor-length with plastered reveals (no architrave).
A13: 4B.1 | B13: Architrave to internal doors, both faces, 18 x 69 (profile by the client) | C13: m | E13: 63.332 | G13: 72.874 | H13: =SUMPRODUCT($D$7:$G$7,D13:G13) | K13: =N(H13)*N(I13) | L13: =N(H13)*N(J13) | M13: =K13+L13 | N13: Order guide +10% = 149.8
A14: 4B.2 | B14: Architrave to the bi-folds (master suite, dining) and the laundry door, inside face | C14: m | E14: 6.081 | G14: 15.77 | H14: =SUMPRODUCT($D$7:$G$7,D14:G14) | K14: =N(H14)*N(I14) | L14: =N(H14)*N(J14) | M14: =K14+L14 | N14: Order guide +10% = 24.0
A15: 4C Window boards (NRM2 22 / package JOI)
B16: Only the two high-level pool-hall windows have a sill above the floor (sill -1,236 = 2,064 above the basement FFL): board = opening + 2 x 50, depth 278 + 25. GF windows are floor-length (threshold, no board).
A17: 4C.1 | B17: Window board 303 x 1,835 long, BL-W01 (pool hall: tiled cill alternative by the pool specialist) | C17: nr | E17: 1 | H17: =SUMPRODUCT($D$7:$G$7,D17:G17) | K17: =N(H17)*N(I17) | L17: =N(H17)*N(J17) | M17: =K17+L17
A18: 4C.2 | B18: Window board 303 x 1,845 long, BL-W02 (pool hall: tiled cill alternative by the pool specialist) | C18: nr | E18: 1 | H18: =SUMPRODUCT($D$7:$G$7,D18:G18) | K18: =N(H18)*N(I18) | L18: =N(H18)*N(J18) | M18: =K18+L18
A19: 4D Stairs and sundry joinery (NRM2 22 / package JOI)
A20: 4D.1 | B20: Staircase basement to GF (rise ~3,300, beside the stair window BL-G04 / L1-G03b) incl. balustrade / handrail - NOT modelled, PROVISIONAL | C20: item | K20: =IF(ISNUMBER(H20),H20,1)*N(I20) | L20: =IF(ISNUMBER(H20),H20,1)*N(J20) | M20: =K20+L20 | N20: Lump sum - the rate entered is the amount. By the stair manufacturer; Standard 4.3 (stairs) - architect
A21: 4D.2 | B21: Guarding / balustrade to the stair well edge at GF (stair / entrance zone) | C21: item | K21: =IF(ISNUMBER(H21),H21,1)*N(I21) | L21: =IF(ISNUMBER(H21),H21,1)*N(J21) | M21: =K21+L21 | N21: Lump sum - the rate entered is the amount. Length to the stair design
A22: 4D.3 | B22: Boxings to services and pipe runs (framing, board, access panels) | C22: item | K22: =IF(ISNUMBER(H22),H22,1)*N(I22) | L22: =IF(ISNUMBER(H22),H22,1)*N(J22) | M22: =K22+L22 | N22: Lump sum - the rate entered is the amount. Allowance - positions to the M&E design
B23: No loft hatch: the GF is vaulted to the ridge throughout (no loft void).
A25: PACKAGE SUMMARY - Bill 4 Joinery - Skirtings, Architraves, Window Boards & Stair (package JOI; amounts by others, excl. VAT)
A26: Section | B26: Description | K26: Supply £ | L26: Install £ | M26: Total £
A27: 4A | B27: Skirtings (NRM2 22 / package JOI) | K27: =SUM(K9:K10) | L27: =SUM(L9:L10) | M27: =SUM(M9:M10)
A28: 4B | B28: Architraves (NRM2 22 / package JOI) | K28: =SUM(K12:K14) | L28: =SUM(L12:L14) | M28: =SUM(M12:M14)
A29: 4C | B29: Window boards (NRM2 22 / package JOI) | K29: =SUM(K16:K18) | L29: =SUM(L16:L18) | M29: =SUM(M16:M18)
A30: 4D | B30: Stairs and sundry joinery (NRM2 22 / package JOI) | K30: =SUM(K20:K23) | L30: =SUM(L20:L23) | M30: =SUM(M20:M23)
A31: PACKAGE TOTAL - Bill 4, carried to the Cover overview | K31: =SUM(K27:K30) | L31: =SUM(L27:L30) | M31: =SUM(M27:M30)
A32: Pale-yellow cells are the only inputs (Supply rate, Install rate). Amounts, subtotals and totals are formulas; the sheet is protected without a password (Review > Unprotect Sheet). Amounts exclude VAT and are NOT part of the Nudura ICF price.

Sheet Bill 5 Partitions
C1: Bill 5 - Timber Stud Partitions (TLSTF) - Framing, Openings, Head Restraint & Fixings
C2: Non-loadbearing 38 x 89 C16 timber stud partitions from the TLSTF model (BF 8 walls 31.4 m / GF 20 walls 43.0 m = 74.4 m, 13 door openings); GF heads raked to the vault. Linings in Bill 2, doorsets in Bill 3. [NRM2 16 / package JOI]
A4: DISCLAIMER: This information is supplied in good faith for guidance and coordination only. It is not part of the Nudura ICF price and must be checked and verified by the appropriate professional (quantity surveyor, designer, engineer or supplier) before use. Only the Nudura ICF formwork and associated accessories are included in our price. Quantities are measured from the BuildEase quotation model of the Foote McBride planning drawings (C2523 PP 01 001-008, raster, no sections / dimensions / levels - heights scaled from the elevations); no allowance for waste is included unless stated. Quantity columns are the model levels P / BL / FB / L1; the Site total is their sum. Rates and amounts are by others.
A6: Ref | B6: Description | C6: Unit | D6: P pool tank | E6: BL basement | F6: FB master footing | G6: L1 ground floor | H6: Site total qty | I6: Supply rate £ | J6: Install rate £ | K6: Supply £ | L6: Install £ | M6: Line total £ | N6: Notes
B7: One building - quantity per level (Site total = sum of the levels) | D7: 1 | E7: 1 | F7: 1 | G7: 1 | H7: =SUM(D7:G7) | N7: Levels: P = pool tank: 3 courses 10in Std, -5,029 to -3,658 (on the pool base); BL = basement: 8 courses 10in Std, FFL -3,300 - garage, laundry, stores, pool hall; FB = master-suite footing: 2 courses 6in XR35, -914 to 0 (no basement under it); L1 = ground floor: 14 courses 6in XR35 incl. the raked gables, vaulted ceilings
A8: 5A Timber stud partitions, non-loadbearing - framing (NRM2 16 / package JOI)
B9: C16 softwood stud partitions as built in the TLSTF model (BF 8 walls 31.4 m / GF 20 walls 43.0 m = 74.4 m, 13 door openings): 38 x 89 studs at 600 c/c (400 in wet rooms), head and bottom rails, noggins. Basement: FFL -3,300 to 5 mm under the GF slab soffit (-325) - 2,975. GF: heads RAKED to 40 mm under the vaulted rafter soffit (z = 5,904.9 - |x - 3,781.6| - 40, KBP_rake_GF.json): 2,439 to 5,865 high - area from the rake profiles. Gross area, door openings NOT deducted (5C). GF studs up to ~5.8 m long: stud size / mid-height restraint of the tall raked walls to the designer.
A10: 5A.1 | B10: Basement partitions (8 walls, 31.4 m): 38 x 89 C16 studs, head + bottom rails, noggins | C10: m2 | E10: 93.303 | H10: =SUMPRODUCT($D$7:$G$7,D10:G10) | K10: =N(H10)*N(I10) | L10: =N(H10)*N(J10) | M10: =K10+L10 | N10: wall length x 2,975
A11: 5A.2 | B11: GF (raked to the vault) partitions (20 walls, 43.0 m): 38 x 89 C16 studs, head + bottom rails, noggins | C11: m2 | G11: 200.934 | H11: =SUMPRODUCT($D$7:$G$7,D11:G11) | K11: =N(H11)*N(I11) | L11: =N(H11)*N(J11) | M11: =K11+L11 | N11: integral of each wall's rake profile
A12: 5B Partition timber - supply (NRM2 16 / package JOI)
B13: ESTIMATE in linear metres of 38 x 89 C16 kiln-dried sawn softwood: studs from the TLSTF verify reports (stud counts x stud height; GF at each wall's mean raked height), bottom rails (door gaps cut out) + head rails (GF along the rake), noggin rows (1 basement; GF 1-3 by height) and 2 king studs + head per door. TLSTF members: basement 348, GF 727. Reconcile against the TLSTF construction extract before ordering. Supply only.
A14: 5B.1 | B14: 38 x 89 C16 kiln-dried sawn softwood: studs (TLSTF stud counts x height) | C14: m | E14: 226.149 | G14: 646.369 | H14: =SUMPRODUCT($D$7:$G$7,D14:G14) | K14: =N(H14)*N(I14) | L14: =N(H14)*N(J14) | M14: =K14+L14 | N14: Estimate - see 5B note
A15: 5B.2 | B15: 38 x 89 C16 kiln-dried sawn softwood: bottom + head rails (GF heads along the rake) | C15: m | E15: 57.699 | G15: 90.017 | H15: =SUMPRODUCT($D$7:$G$7,D15:G15) | K15: =N(H15)*N(I15) | L15: =N(H15)*N(J15) | M15: =K15+L15 | N15: Estimate - see 5B note
A16: 5B.3 | B16: 38 x 89 C16 kiln-dried sawn softwood: noggins | C16: m | E16: 26.336 | G16: 103.818 | H16: =SUMPRODUCT($D$7:$G$7,D16:G16) | K16: =N(H16)*N(I16) | L16: =N(H16)*N(J16) | M16: =K16+L16 | N16: Estimate - see 5B note
A17: 5B.4 | B17: 38 x 89 C16 kiln-dried sawn softwood: king studs and heads at door openings | C17: m | E17: 40.726 | G17: 67.325 | H17: =SUMPRODUCT($D$7:$G$7,D17:G17) | K17: =N(H17)*N(I17) | L17: =N(H17)*N(J17) | M17: =K17+L17 | N17: Estimate - see 5B note
A18: 5B.5 | B18: 38 x 89 C16 lengths to order (run +10%; basement 4.8 m, GF 6.0 m lengths for the tall raked studs) | C18: nr | E18: 81 | G18: 167 | H18: =SUMPRODUCT($D$7:$G$7,D18:G18) | M18: not priced | N18: Ordering guide only - not priced in addition
A19: 5C Forming door openings in partitions (NRM2 16 / package JOI)
B20: From the TLSTF door report (13 openings). Per opening: 2 full-height king studs, head at ~2,100, cripples over, bottom rail cut out. Timber in 5B.
A21: 5C.1 | B21: Form door opening 680 wide x ~2,100 high in the 89 partition | C21: nr | G21: 3 | H21: =SUMPRODUCT($D$7:$G$7,D21:G21) | K21: =N(H21)*N(I21) | L21: =N(H21)*N(J21) | M21: =K21+L21 | N21: Doorsets in Bill 3
A22: 5C.2 | B22: Form door opening 762 wide x ~2,100 high in the 89 partition | C22: nr | G22: 1 | H22: =SUMPRODUCT($D$7:$G$7,D22:G22) | K22: =N(H22)*N(I22) | L22: =N(H22)*N(J22) | M22: =K22+L22 | N22: Doorsets in Bill 3
A23: 5C.3 | B23: Form door opening 800 wide x ~2,100 high in the 89 partition | C23: nr | E23: 1 | H23: =SUMPRODUCT($D$7:$G$7,D23:G23) | K23: =N(H23)*N(I23) | L23: =N(H23)*N(J23) | M23: =K23+L23 | N23: Doorsets in Bill 3
A24: 5C.4 | B24: Form door opening 830 wide x ~2,100 high in the 89 partition | C24: nr | E24: 1 | H24: =SUMPRODUCT($D$7:$G$7,D24:G24) | K24: =N(H24)*N(I24) | L24: =N(H24)*N(J24) | M24: =K24+L24 | N24: Doorsets in Bill 3
A25: 5C.5 | B25: Form door opening 846 wide x ~2,100 high in the 89 partition | C25: nr | E25: 1 | H25: =SUMPRODUCT($D$7:$G$7,D25:G25) | K25: =N(H25)*N(I25) | L25: =N(H25)*N(J25) | M25: =K25+L25 | N25: Doorsets in Bill 3
A26: 5C.6 | B26: Form door opening 850 wide x ~2,100 high in the 89 partition | C26: nr | E26: 3 | G26: 2 | H26: =SUMPRODUCT($D$7:$G$7,D26:G26) | K26: =N(H26)*N(I26) | L26: =N(H26)*N(J26) | M26: =K26+L26 | N26: Doorsets in Bill 3
A27: 5C.7 | B27: Form door opening 855 wide x ~2,100 high in the 89 partition | C27: nr | G27: 1 | H27: =SUMPRODUCT($D$7:$G$7,D27:G27) | K27: =N(H27)*N(I27) | L27: =N(H27)*N(J27) | M27: =K27+L27 | N27: Doorsets in Bill 3
A28: 5D Head restraint, pattresses, acoustic and fixings (NRM2 16 / package JOI)
B29: Basement heads: galvanised slotted deflection head clips to the GF slab soffit (TLSTF head-restraint report, 5 mm gap). GF heads are raked to the rafters: fix the head rail to the rafters / noggins between rafters (no report - estimated at 600 c/c along the rake). Bottom rails fixed to the slab / screed on a DPC strip. Pattresses: 18 WBP ply in the stud bays on the wet-room faces, 150-1,950 above floor (KBP pattress reports).
A30: 5D.1 | B30: Slotted deflection head clip, galvanised, partition head to the GF slab soffit (product to confirm) | C30: nr | E30: 122 | H30: =SUMPRODUCT($D$7:$G$7,D30:G30) | K30: =N(H30)*N(I30) | L30: =N(H30)*N(J30) | M30: =K30+L30 | N30: TLSTF head-restraint report BF
A31: 5D.2 | B31: Raked head rail fixed to the rafters / noggins between rafters (screws / angle brackets) at ~600 c/c | C31: nr | G31: 88 | H31: =SUMPRODUCT($D$7:$G$7,D31:G31) | K31: =N(H31)*N(I31) | L31: =N(H31)*N(J31) | M31: =K31+L31 | N31: Estimate along the rake profiles
A32: 5D.3 | B32: Fix bottom rails to the slab / screed: concrete screws at max 600 c/c on a DPC strip | C32: m | E32: 26.336 | G32: 37.639 | H32: =SUMPRODUCT($D$7:$G$7,D32:G32) | K32: =N(H32)*N(I32) | L32: =N(H32)*N(J32) | M32: =K32+L32 | N32: Bottom rail length (door gaps excluded)
A33: 5D.4 | B33: 18 mm WBP plywood pattress pieces between studs (wet-room faces: ensuites, cloaks, laundry) | C33: nr | E33: 34 | G33: 86 | H33: =SUMPRODUCT($D$7:$G$7,D33:G33) | K33: =N(H33)*N(I33) | L33: =N(H33)*N(J33) | M33: =K33+L33 | N33: BL: laundry; L1: ensuite (master), cloaks, ensuite (bed 3)
A34: 5D.5 | B34: Acoustic mineral wool quilt in the partition voids (bedrooms / bathrooms) where required by Standard 5.2 (noise reduction between rooms) | C34: item | K34: =IF(ISNUMBER(H34),H34,1)*N(I34) | L34: =IF(ISNUMBER(H34),H34,1)*N(J34) | M34: =K34+L34 | N34: Lump sum - the rate entered is the amount. Allowance - architect
A35: 5D.6 | B35: Nails, screws, framing fixings and sundries for the partition framing | C35: item | K35: =IF(ISNUMBER(H35),H35,1)*N(I35) | L35: =IF(ISNUMBER(H35),H35,1)*N(J35) | M35: =K35+L35 | N35: Lump sum - the rate entered is the amount.
A37: PACKAGE SUMMARY - Bill 5 Timber Stud Partitions (TLSTF) - Framing, Openings, Head Restraint & Fixings (package JOI; amounts by others, excl. VAT)
A38: Section | B38: Description | K38: Supply £ | L38: Install £ | M38: Total £
A39: 5A | B39: Timber stud partitions, non-loadbearing - framing (NRM2 16 / package JOI) | K39: =SUM(K9:K11) | L39: =SUM(L9:L11) | M39: =SUM(M9:M11)
A40: 5B | B40: Partition timber - supply (NRM2 16 / package JOI) | K40: =SUM(K13:K18) | L40: =SUM(L13:L18) | M40: =SUM(M13:M18)
A41: 5C | B41: Forming door openings in partitions (NRM2 16 / package JOI) | K41: =SUM(K20:K27) | L41: =SUM(L20:L27) | M41: =SUM(M20:M27)
A42: 5D | B42: Head restraint, pattresses, acoustic and fixings (NRM2 16 / package JOI) | K42: =SUM(K29:K35) | L42: =SUM(L29:L35) | M42: =SUM(M29:M35)
A43: PACKAGE TOTAL - Bill 5, carried to the Cover overview | K43: =SUM(K39:K42) | L43: =SUM(L39:L42) | M43: =SUM(M39:M42)
A44: Pale-yellow cells are the only inputs (Supply rate, Install rate). Amounts, subtotals and totals are formulas; the sheet is protected without a password (Review > Unprotect Sheet). Amounts exclude VAT and are NOT part of the Nudura ICF price.

Sheet Bill 6 Slabs
C1: Bill 6 - Substructure & Slabs - Pool Base, Raft, GF Slab, Floor Build-ups (coordination)
C2: Coordination quantities for the engineer / groundworker / frame contractor: pool base, basement raft, GF suspended slab, floor build-ups (by others). [NRM2 11 / package RCF / FLR]
A4: DISCLAIMER: This information is supplied in good faith for guidance and coordination only. It is not part of the Nudura ICF price and must be checked and verified by the appropriate professional (quantity surveyor, designer, engineer or supplier) before use. Only the Nudura ICF formwork and associated accessories are included in our price. Quantities are measured from the BuildEase quotation model of the Foote McBride planning drawings (C2523 PP 01 001-008, raster, no sections / dimensions / levels - heights scaled from the elevations); no allowance for waste is included unless stated. Quantity columns are the model levels P / BL / FB / L1; the Site total is their sum. Rates and amounts are by others.
A6: Ref | B6: Description | C6: Unit | D6: P pool tank | E6: BL basement | F6: FB master footing | G6: L1 ground floor | H6: Site total qty | I6: Supply rate £ | J6: Install rate £ | K6: Supply £ | L6: Install £ | M6: Line total £ | N6: Notes
B7: One building - quantity per level (Site total = sum of the levels) | D7: 1 | E7: 1 | F7: 1 | G7: 1 | H7: =SUM(D7:G7) | N7: Levels: P = pool tank: 3 courses 10in Std, -5,029 to -3,658 (on the pool base); BL = basement: 8 courses 10in Std, FFL -3,300 - garage, laundry, stores, pool hall; FB = master-suite footing: 2 courses 6in XR35, -914 to 0 (no basement under it); L1 = ground floor: 14 courses 6in XR35 incl. the raked gables, vaulted ceilings
A8: 6A RC base, raft and slabs (NRM2 11 - package RCF; by others - engineer; coordination quantities)
B9: Volumes and areas are the model slab groups (04_Logs/build/floors.json from KB_slabs.json - ALL INDICATIVE, the engineer designs them). NOT in the Nudura price and NOT in the ICF BOQ Builder bill (which carries the ICF wall concrete only). Reinforcement at a provisional 100 kg/m3. Basement raft and pool base: water-resisting concrete (BS 8102 Type B) - see Bill 9.
A10: 6A.1 | B10: Pool base, 300 RC, top -5,029 (under the ICF pool tank) | C10: m3 | D10: 17.87 | H10: =SUMPRODUCT($D$7:$G$7,D10:G10) | K10: =N(H10)*N(I10) | L10: =N(H10)*N(J10) | M10: =K10+L10 | N10: 59.58 m2
A11: 6A.2 | B11: Basement raft, 300 RC, top -3,658, 300 toe, hole for the pool tank | C11: m3 | E11: 53.2 | H11: =SUMPRODUCT($D$7:$G$7,D11:G11) | K11: =N(H11)*N(I11) | L11: =N(H11)*N(J11) | M11: =K11+L11 | N11: 177.35 m2
A12: 6A.3 | B12: GF suspended RC slab 250, top -75, over the basement, the pool and the 7.5 m garage (stair / entrance zone open) | C12: m3 | G12: 47.03 | H12: =SUMPRODUCT($D$7:$G$7,D12:G12) | K12: =N(H12)*N(I12) | L12: =N(H12)*N(J12) | M12: =K12+L12 | N12: 188.11 m2 - engineer (spans, posts on it)
A13: 6A.4 | B13: Soffit falsework / propping to the GF slab (props ~3.0 m over the basement, ~4.7 m over the pool) incl. back-propping | C13: m2 | G13: 183.721 | H13: =SUMPRODUCT($D$7:$G$7,D13:G13) | K13: =N(H13)*N(I13) | L13: =N(H13)*N(J13) | M13: =K13+L13 | N13: Basement 140.3 + pool hall 43.4 - PROVISIONAL
A14: 6A.5 | B14: Edge formwork to the GF slab at the stair / entrance opening (250 deep) | C14: m2 | G14: 1.197 | H14: =SUMPRODUCT($D$7:$G$7,D14:G14) | K14: =N(H14)*N(I14) | L14: =N(H14)*N(J14) | M14: =K14+L14 | N14: Other edges cast against the ICF inner face
A15: 6A.6 | B15: Reinforcement to the base / raft / slabs, provisional 100 kg/m3, incl. starters into the ICF cores | C15: t | D15: 1.787 | E15: 5.32 | F15: 0.398 | G15: 4.703 | H15: =SUMPRODUCT($D$7:$G$7,D15:G15) | K15: =N(H15)*N(I15) | L15: =N(H15)*N(J15) | M15: =K15+L15 | N15: PROVISIONAL - engineer
A16: 6B Floor build-ups (NRM2 11 / 28 - package FLR; by others)
A17: 6B.1 | B17: Basement floor: 150 PIR insulation on the raft (with the BS 8102 membrane / drainage layer per Bill 9) | C17: m2 | E17: 140.32 | H17: =SUMPRODUCT($D$7:$G$7,D17:G17) | K17: =N(H17)*N(I17) | L17: =N(H17)*N(J17) | M17: =K17+L17 | N17: 21.05 m3
A18: 6B.2 | B18: Basement floor: UFH screed + levelling, 207.6 average to FFL -3,300 (UFH pipework by the M&E contractor) | C18: m2 | E18: 140.32 | H18: =SUMPRODUCT($D$7:$G$7,D18:G18) | K18: =N(H18)*N(I18) | L18: =N(H18)*N(J18) | M18: =K18+L18 | N18: 29.13 m3
A19: 6B.3 | B19: GF screed 75 on the suspended slab (UFH by M&E if specified) | C19: m2 | G19: 188.11 | H19: =SUMPRODUCT($D$7:$G$7,D19:G19) | K19: =N(H19)*N(I19) | L19: =N(H19)*N(J19) | M19: =K19+L19 | N19: 14.11 m3
A20: 6B.4 | B20: Master suite ground-bearing floor (inside the FB footing walls): 200 compacted hardcore | C20: m2 | F20: 19.89 | H20: =SUMPRODUCT($D$7:$G$7,D20:G20) | K20: =N(H20)*N(I20) | L20: =N(H20)*N(J20) | M20: =K20+L20 | N20: 3.98 m3
A21: 6B.5 | B21: Master suite ground-bearing floor (inside the FB footing walls): 200 RC ground-bearing slab on DPM | C21: m2 | F21: 19.89 | H21: =SUMPRODUCT($D$7:$G$7,D21:G21) | K21: =N(H21)*N(I21) | L21: =N(H21)*N(J21) | M21: =K21+L21 | N21: 3.98 m3
A22: 6B.6 | B22: Master suite ground-bearing floor (inside the FB footing walls): 135 PIR insulation | C22: m2 | F22: 19.89 | H22: =SUMPRODUCT($D$7:$G$7,D22:G22) | K22: =N(H22)*N(I22) | L22: =N(H22)*N(J22) | M22: =K22+L22 | N22: 2.69 m3
A23: 6B.7 | B23: Master suite ground-bearing floor (inside the FB footing walls): 65 sand/cement screed | C23: m2 | F23: 19.89 | H23: =SUMPRODUCT($D$7:$G$7,D23:G23) | K23: =N(H23)*N(I23) | L23: =N(H23)*N(J23) | M23: =K23+L23 | N23: 1.29 m3
A24: 6B.8 | B24: Master suite: DPM / gas membrane under the slab (per the site radon / ground-gas assessment) | C24: m2 | F24: 19.89 | H24: =SUMPRODUCT($D$7:$G$7,D24:G24) | K24: =N(H24)*N(I24) | L24: =N(H24)*N(J24) | M24: =K24+L24 | N24: Lapped and sealed to the ICF
A25: 6C Coordination
A26: 6C.1 | B26: Ridge-post bearings on the GF slab (100 x 100 x 8 SHS at x 3,781.6, y 5,580, 9,008, 13,713): base plates, fixings and the point-load path - they land on the GF slab OVER THE POOL TANK (engineer: downstand / transfer or posts carried to the pool walls) | C26: nr | G26: 3 | H26: =SUMPRODUCT($D$7:$G$7,D26:G26) | K26: =N(H26)*N(I26) | L26: =N(H26)*N(J26) | M26: =K26+L26 | N26: ENGINEER - flag
A28: PACKAGE SUMMARY - Bill 6 Substructure & Slabs - Pool Base, Raft, GF Slab, Floor Build-ups (coordination) (package RCF / FLR; amounts by others, excl. VAT)
A29: Section | B29: Description | K29: Supply £ | L29: Install £ | M29: Total £
A30: 6A | B30: RC base, raft and slabs (NRM2 11 - package RCF; by others - engineer; coordination quantities) | K30: =SUM(K9:K15) | L30: =SUM(L9:L15) | M30: =SUM(M9:M15)
A31: 6B | B31: Floor build-ups (NRM2 11 / 28 - package FLR; by others) | K31: =SUM(K17:K24) | L31: =SUM(L17:L24) | M31: =SUM(M17:M24)
A32: 6C | B32: Coordination | K32: =SUM(K26:K26) | L32: =SUM(L26:L26) | M32: =SUM(M26:M26)
A33: PACKAGE TOTAL - Bill 6, carried to the Cover overview | K33: =SUM(K30:K32) | L33: =SUM(L30:L32) | M33: =SUM(M30:M32)
A34: Pale-yellow cells are the only inputs (Supply rate, Install rate). Amounts, subtotals and totals are formulas; the sheet is protected without a password (Review > Unprotect Sheet). Amounts exclude VAT and are NOT part of the Nudura ICF price.

Sheet Bill 7 Roof
C1: Bill 7 - Vaulted Roof - Structure, Covering, Rainwater & Insulation
C2: Vaulted cut roof (63 x 220 C24 rafters on ridge beams + SHS posts), slate / tile covering, eaves, valley, rainwater, rooflights and the warm-vault insulation. [NRM2 16 / 18 / package RFS / RFC]
A4: DISCLAIMER: This information is supplied in good faith for guidance and coordination only. It is not part of the Nudura ICF price and must be checked and verified by the appropriate professional (quantity surveyor, designer, engineer or supplier) before use. Only the Nudura ICF formwork and associated accessories are included in our price. Quantities are measured from the BuildEase quotation model of the Foote McBride planning drawings (C2523 PP 01 001-008, raster, no sections / dimensions / levels - heights scaled from the elevations); no allowance for waste is included unless stated. Quantity columns are the model levels P / BL / FB / L1; the Site total is their sum. Rates and amounts are by others.
A6: Ref | B6: Description | C6: Unit | D6: P pool tank | E6: BL basement | F6: FB master footing | G6: L1 ground floor | H6: Site total qty | I6: Supply rate £ | J6: Install rate £ | K6: Supply £ | L6: Install £ | M6: Line total £ | N6: Notes
B7: One building - quantity per level (Site total = sum of the levels) | D7: 1 | E7: 1 | F7: 1 | G7: 1 | H7: =SUM(D7:G7) | N7: Levels: P = pool tank: 3 courses 10in Std, -5,029 to -3,658 (on the pool base); BL = basement: 8 courses 10in Std, FFL -3,300 - garage, laundry, stores, pool hall; FB = master-suite footing: 2 courses 6in XR35, -914 to 0 (no basement under it); L1 = ground floor: 14 courses 6in XR35 incl. the raked gables, vaulted ceilings
A8: 7A Roof structure - vaulted cut roof (NRM2 16 - package RFS; roof designer / engineer)
B9: Two 45 deg gable roofs with ridges along y, VAULTED with a ridge (Tom 20.10; KBS RoofStruct: system cut_ridge, rafters 63 x 220 C24 @ 600, heel auto; Douglas ~220 m AOD, snow zone 4 / vb 25.5 assumed). Roof L (wing + hall): ridge 120 x 400 GL24h on 5 bearings (gables + 3 SHS posts); Roof R (lounge + dining): 140 x 800 GL24h glulam ridge on 2 bearings over 12.3 m (special order; rear bearing = the glazed dining gable - engineer). RoofStruct built 109 + 81 members with 0 warnings; the rafter counts below are computed from the roof geometry (ridges x 3,781.6 / 11,210, valley x 7,461.6, eaves overhang 300, verge 150) - reconcile with the RoofStruct cutting list. Rooflights: 5 on the east slope of Roof L (east elevation; NOT modelled) - each trimmed with a double rafter each side and double trimmers (Tom 09.10).
A10: 7A.1 | B10: Rafter 63 x 220 C24 @ 600, Roof L east slope (eaves to ridge): 5.61 m on the slope (birdsmouth on the plate / valley, cut to the ridge) | C10: nr | G10: 35 | H10: =SUMPRODUCT($D$7:$G$7,D10:G10) | K10: =N(H10)*N(I10) | L10: =N(H10)*N(J10) | M10: =K10+L10
A11: 7A.2 | B11: Rafter 63 x 220 C24 @ 600, Roof L west slope to the valley: 5.05 m on the slope (birdsmouth on the plate / valley, cut to the ridge) | C11: nr | G11: 19 | H11: =SUMPRODUCT($D$7:$G$7,D11:G11) | K11: =N(H11)*N(I11) | L11: =N(H11)*N(J11) | M11: =K11+L11
A12: 7A.3 | B12: Rafter 63 x 220 C24 @ 600, Roof L west slope to its eaves (outside Roof R): 5.33 m on the slope (birdsmouth on the plate / valley, cut to the ridge) | C12: nr | G12: 16 | H12: =SUMPRODUCT($D$7:$G$7,D12:G12) | K12: =N(H12)*N(I12) | L12: =N(H12)*N(J12) | M12: =K12+L12
A13: 7A.4 | B13: Rafter 63 x 220 C24 @ 600, Roof R east slope (valley to ridge): 5.20 m on the slope (birdsmouth on the plate / valley, cut to the ridge) | C13: nr | G13: 20 | H13: =SUMPRODUCT($D$7:$G$7,D13:G13) | K13: =N(H13)*N(I13) | L13: =N(H13)*N(J13) | M13: =K13+L13
A14: 7A.5 | B14: Rafter 63 x 220 C24 @ 600, Roof R west slope (eaves to ridge): 5.77 m on the slope (birdsmouth on the plate / valley, cut to the ridge) | C14: nr | G14: 20 | H14: =SUMPRODUCT($D$7:$G$7,D14:G14) | K14: =N(H14)*N(I14) | L14: =N(H14)*N(J14) | M14: =K14+L14
A15: 7A.6 | B15: Additional rafter 63 x 220 C24 doubling each side of the 5 rooflights (5.61 m) | C15: nr | G15: 10 | H15: =SUMPRODUCT($D$7:$G$7,D15:G15) | K15: =N(H15)*N(I15) | L15: =N(H15)*N(J15) | M15: =K15+L15 | N15: Tom 09.10 roof-window rule
A16: 7A.7 | B16: Rafters 63 x 220 C24 - total length (all of the above) | C16: m | G16: 653.104 | H16: =SUMPRODUCT($D$7:$G$7,D16:G16) | M16: not priced | N16: Order guide +10% = 718.4
A17: 7A.8 | B17: Double trimmers 63 x 220 C24 at the rooflight heads and sills (4 pieces per rooflight, ~0.65 m) | C17: nr | G17: 20 | H17: =SUMPRODUCT($D$7:$G$7,D17:G17) | K17: =N(H17)*N(I17) | L17: =N(H17)*N(J17) | M17: =K17+L17
A18: 7A.9 | B18: Roof L ridge beam 120 x 400 GL24h glulam, ~20.7 m on the two gables + 3 SHS posts (continuous over 5 bearings - delivery length / splice per the engineer) | C18: nr | G18: 1 | H18: =SUMPRODUCT($D$7:$G$7,D18:G18) | K18: =N(H18)*N(I18) | L18: =N(H18)*N(J18) | M18: =K18+L18 | N18: ENGINEER - 20.7 m piece: splice over a post if not deliverable
A19: 7A.10 | B19: Roof R ridge beam 140 x 800 GL24h glulam, ~12.3 m, bearing on the lounge front gable and the glazed dining gable (special order) | C19: nr | G19: 1 | H19: =SUMPRODUCT($D$7:$G$7,D19:G19) | K19: =N(H19)*N(I19) | L19: =N(H19)*N(J19) | M19: =K19+L19 | N19: ENGINEER - rear bearing on the glazed gable
A20: 7A.11 | B20: Steel ridge posts 100 x 100 x 8 SHS, 5,891 long (GF slab -75 to the ridge soffit 5,816), base + cap plates, fire protection where exposed | C20: nr | G20: 3 | H20: =SUMPRODUCT($D$7:$G$7,D20:G20) | K20: =N(H20)*N(I20) | L20: =N(H20)*N(J20) | M20: =K20+L20 | N20: In the wing partitions (y 5,580 / 9,008 / 13,713)
A21: 7A.12 | B21: Wall plate on the ICF eaves walls (wing east, block west, stair pier), bedded and anchored to the ICF core | C21: m | G21: 32.086 | H21: =SUMPRODUCT($D$7:$G$7,D21:G21) | K21: =N(H21)*N(I21) | L21: =N(H21)*N(J21) | M21: =K21+L21 | N21: Order guide +10% = 35.3
A22: 7A.13 | B22: Holding-down straps / anchor bolts, wall plate to the ICF, at ~1.2 m c/c | C22: nr | G22: 33 | H22: =SUMPRODUCT($D$7:$G$7,D22:G22) | K22: =N(H22)*N(I22) | L22: =N(H22)*N(J22) | M22: =K22+L22 | N22: Spacing per the engineer
A23: 7A.14 | B23: Gable ladders at the verges (150 verge) incl. fixings to the gable | C23: m | G23: 44.854 | H23: =SUMPRODUCT($D$7:$G$7,D23:G23) | K23: =N(H23)*N(I23) | L23: =N(H23)*N(J23) | M23: =K23+L23 | N23: 4 gable ends (front + rear of both roofs)
A24: 7A.15 | B24: Valley between Roof L and Roof R (x 7,461.6): valley boards / lay boards and support | C24: m | G24: 11.955 | H24: =SUMPRODUCT($D$7:$G$7,D24:G24) | K24: =N(H24)*N(I24) | L24: =N(H24)*N(J24) | M24: =K24+L24
A25: 7A.16 | B25: Rafter fixings: rafter-to-ridge connectors (hangers / straps) and rafter-to-plate / valley fixings (2 per rafter) | C25: nr | G25: 240 | H25: =SUMPRODUCT($D$7:$G$7,D25:G25) | K25: =N(H25)*N(I25) | L25: =N(H25)*N(J25) | M25: =K25+L25
A26: 7B Roof covering, eaves, verges and rainwater (NRM2 18 / 33 - package RFC)
B27: Slope areas = plan x 1.414 (45 deg). Plan: Roof L 162.8 m2 (east slope + west slope to the valley / its eaves), Roof R 96.8 m2, incl. the 300 eaves overhangs and 150 verges. Covering: the elevations are hatched as slate / tile - product per the planning approval (TBC; Scotland - natural slate is common).
A28: 7B.1 | B28: Roof covering, slate / tile (spec TBC) on battens + counter-battens, measured on the slope | C28: m2 | G28: 367.064 | H28: =SUMPRODUCT($D$7:$G$7,D28:G28) | K28: =N(H28)*N(I28) | L28: =N(H28)*N(J28) | M28: =K28+L28 | N28: Order guide +10% = 403.8
A29: 7B.2 | B29: Breathable roof membrane (vapour-permeable underlay) with laps, on the rafters / sarking | C29: m2 | G29: 367.064 | H29: =SUMPRODUCT($D$7:$G$7,D29:G29) | K29: =N(H29)*N(I29) | L29: =N(H29)*N(J29) | M29: =K29+L29 | N29: Order guide +15% = 422.1
A30: 7B.3 | B30: Ridge (Roof L 20.7 m + Roof R 12.3 m): ridge tiles / dry ridge system incl. ventilation | C30: m | G30: 33 | H30: =SUMPRODUCT($D$7:$G$7,D30:G30) | K30: =N(H30)*N(I30) | L30: =N(H30)*N(J30) | M30: =K30+L30
A31: 7B.4 | B31: Verges: undercloak + dry verge / mortar verge, front and rear gables of both roofs | C31: m | G31: 44.854 | H31: =SUMPRODUCT($D$7:$G$7,D31:G31) | K31: =N(H31)*N(I31) | L31: =N(H31)*N(J31) | M31: =K31+L31
A32: 7B.5 | B32: Valley gutter / lining between the two roofs (lead or GRP) incl. outlets at the ends | C32: m | G32: 11.955 | H32: =SUMPRODUCT($D$7:$G$7,D32:G32) | K32: =N(H32)*N(I32) | L32: =N(H32)*N(J32) | M32: =K32+L32 | N32: Valley between parallel ridges - designer
A33: 7B.6 | B33: Eaves: fascia, soffit (300 overhang), eaves ventilation / protection tray | C33: m | G33: 41.49 | H33: =SUMPRODUCT($D$7:$G$7,D33:G33) | K33: =N(H33)*N(I33) | L33: =N(H33)*N(J33) | M33: =K33+L33 | N33: Roof L east, Roof L west outside Roof R, Roof R west
A34: 7B.7 | B34: Eaves gutters (PVC-u / aluminium) incl. stop ends, outlets, brackets | C34: m | G34: 41.49 | H34: =SUMPRODUCT($D$7:$G$7,D34:G34) | K34: =N(H34)*N(I34) | L34: =N(H34)*N(J34) | M34: =K34+L34 | N34: Order guide +5% = 43.6
A35: 7B.8 | B35: Downpipes from the eaves gutters and the valley outlets to the drainage (number / positions TBC) | C35: nr | G35: 6 | H35: =SUMPRODUCT($D$7:$G$7,D35:G35) | K35: =N(H35)*N(I35) | L35: =N(H35)*N(J35) | M35: =K35+L35 | N35: PROVISIONAL - drainage design
A36: 7B.9 | B36: Rooflights (east slope of Roof L, ~0.7 x 1.0 m scaled - size TBC) incl. flashing kits and internal linings | C36: nr | G36: 5 | H36: =SUMPRODUCT($D$7:$G$7,D36:G36) | K36: =N(H36)*N(I36) | L36: =N(H36)*N(J36) | M36: =K36+L36 | N36: Seen on the east elevation - NOT modelled
A37: 7B.10 | B37: Chimney / stove flue through the lounge roof (drawn, NOT modelled): flue system, flashings, terminal | C37: item | K37: =IF(ISNUMBER(H37),H37,1)*N(I37) | L37: =IF(ISNUMBER(H37),H37,1)*N(J37) | M37: =K37+L37 | N37: Lump sum - the rate entered is the amount. Not measured
A38: 7C Roof insulation, VCL and soffits (NRM2 18 / 28 - package RFC)
B39: Warm vault: insulation between the 220 rafters plus an insulated layer under (or over) them, VCL on the warm side, plasterboard in Bill 2B.4. Build-up and U-value by the SAP assessor (Standard 6.2, Section 6 Energy). Measured as the GF vaulted ceiling area on the slope.
A40: 7C.1 | B40: Insulation between the rafters (to suit 220 deep, ventilated or full-fill per the build-up) + insulated board under the rafters | C40: m2 | G40: 282.549 | H40: =SUMPRODUCT($D$7:$G$7,D40:G40) | K40: =N(H40)*N(I40) | L40: =N(H40)*N(J40) | M40: =K40+L40 | N40: Order guide +5% = 296.7
A41: 7C.2 | B41: Vapour control layer on the warm side, taped laps and penetrations | C41: m2 | G41: 282.549 | H41: =SUMPRODUCT($D$7:$G$7,D41:G41) | K41: =N(H41)*N(I41) | L41: =N(H41)*N(J41) | M41: =K41+L41 | N41: Order guide +10% = 310.8
A42: 7C.3 | B42: External soffit lining under the roof over the master-suite covered terrace (on the slope) | C42: m2 | G42: 17.566 | H42: =SUMPRODUCT($D$7:$G$7,D42:G42) | K42: =N(H42)*N(I42) | L42: =N(H42)*N(J42) | M42: =K42+L42 | N42: PROVISIONAL - plan ~12.4 m2
A44: PACKAGE SUMMARY - Bill 7 Vaulted Roof - Structure, Covering, Rainwater & Insulation (package RFS / RFC; amounts by others, excl. VAT)
A45: Section | B45: Description | K45: Supply £ | L45: Install £ | M45: Total £
A46: 7A | B46: Roof structure - vaulted cut roof (NRM2 16 - package RFS; roof designer / engineer) | K46: =SUM(K9:K25) | L46: =SUM(L9:L25) | M46: =SUM(M9:M25)
A47: 7B | B47: Roof covering, eaves, verges and rainwater (NRM2 18 / 33 - package RFC) | K47: =SUM(K27:K37) | L47: =SUM(L27:L37) | M47: =SUM(M27:M37)
A48: 7C | B48: Roof insulation, VCL and soffits (NRM2 18 / 28 - package RFC) | K48: =SUM(K39:K42) | L48: =SUM(L39:L42) | M48: =SUM(M39:M42)
A49: PACKAGE TOTAL - Bill 7, carried to the Cover overview | K49: =SUM(K46:K48) | L49: =SUM(L46:L48) | M49: =SUM(M46:M48)
A50: Pale-yellow cells are the only inputs (Supply rate, Install rate). Amounts, subtotals and totals are formulas; the sheet is protected without a password (Review > Unprotect Sheet). Amounts exclude VAT and are NOT part of the Nudura ICF price.

Sheet Bill 8 Glazing
C1: Bill 8 - Glazing, External Doors, Raked Feature Screens & Garage Door
C2: Windows, external doors, stair screens and the raked feature screens to the vault from the BuildEase window fit; guarding, garage door and unmodelled glazing provisional. [NRM2 25 / package WIN / GLZ]
A4: DISCLAIMER: This information is supplied in good faith for guidance and coordination only. It is not part of the Nudura ICF price and must be checked and verified by the appropriate professional (quantity surveyor, designer, engineer or supplier) before use. Only the Nudura ICF formwork and associated accessories are included in our price. Quantities are measured from the BuildEase quotation model of the Foote McBride planning drawings (C2523 PP 01 001-008, raster, no sections / dimensions / levels - heights scaled from the elevations); no allowance for waste is included unless stated. Quantity columns are the model levels P / BL / FB / L1; the Site total is their sum. Rates and amounts are by others.
A6: Ref | B6: Description | C6: Unit | D6: P pool tank | E6: BL basement | F6: FB master footing | G6: L1 ground floor | H6: Site total qty | I6: Supply rate £ | J6: Install rate £ | K6: Supply £ | L6: Install £ | M6: Line total £ | N6: Notes
B7: One building - quantity per level (Site total = sum of the levels) | D7: 1 | E7: 1 | F7: 1 | G7: 1 | H7: =SUM(D7:G7) | N7: Levels: P = pool tank: 3 courses 10in Std, -5,029 to -3,658 (on the pool base); BL = basement: 8 courses 10in Std, FFL -3,300 - garage, laundry, stores, pool hall; FB = master-suite footing: 2 courses 6in XR35, -914 to 0 (no basement under it); L1 = ground floor: 14 courses 6in XR35 incl. the raked gables, vaulted ceilings
A8: 8A Windows - UPVC casements (NRM2 25 - package WIN; window supplier)
B9: From the BuildEase window fit (fbw_fit.json; KBW): structural opening sizes (so) and lights. ALL GF windows are FLOOR-LENGTH (sill at FFL): safety glazing in critical locations (Standard 4.8) - toughened / laminated to the lower panes at least. Frames tight to the back of the outer EPS.
A10: 8A.1 | B10: UPVC casement window 1,256 x 2,076 so, 2 lights, DGU (floor-length, safety glazing) | C10: nr | G10: 3 | H10: =SUMPRODUCT($D$7:$G$7,D10:G10) | K10: =N(H10)*N(I10) | L10: =N(H10)*N(J10) | M10: =K10+L10 | N10: L1-W01, L1-W07, L1-W08
A11: 8A.2 | B11: UPVC casement window 1,251 x 2,076 so, 2 lights, DGU (floor-length, safety glazing) | C11: nr | G11: 2 | H11: =SUMPRODUCT($D$7:$G$7,D11:G11) | K11: =N(H11)*N(I11) | L11: =N(H11)*N(J11) | M11: =K11+L11 | N11: L1-W02, L1-W05
A12: 8A.3 | B12: UPVC casement window 2,036 x 2,076 so, 3 lights, DGU (floor-length, safety glazing) | C12: nr | G12: 1 | H12: =SUMPRODUCT($D$7:$G$7,D12:G12) | K12: =N(H12)*N(I12) | L12: =N(H12)*N(J12) | M12: =K12+L12 | N12: L1-W03
A13: 8A.4 | B13: UPVC casement window 1,051 x 2,076 so, 1 light, DGU (floor-length, safety glazing) | C13: nr | G13: 1 | H13: =SUMPRODUCT($D$7:$G$7,D13:G13) | K13: =N(H13)*N(I13) | L13: =N(H13)*N(J13) | M13: =K13+L13 | N13: L1-W04
A14: 8A.5 | B14: UPVC casement window 1,241 x 2,076 so, 2 lights, DGU (floor-length, safety glazing) | C14: nr | G14: 1 | H14: =SUMPRODUCT($D$7:$G$7,D14:G14) | K14: =N(H14)*N(I14) | L14: =N(H14)*N(J14) | M14: =K14+L14 | N14: L1-W06
A15: 8A.6 | B15: UPVC casement window 1,735 x 898 so, 3 lights, DGU (pool hall: high-level, humidity-rated) | C15: nr | E15: 1 | H15: =SUMPRODUCT($D$7:$G$7,D15:G15) | K15: =N(H15)*N(I15) | L15: =N(H15)*N(J15) | M15: =K15+L15 | N15: BL-W01
A16: 8A.7 | B16: UPVC casement window 1,746 x 898 so, 3 lights, DGU (pool hall: high-level, humidity-rated) | C16: nr | E16: 1 | H16: =SUMPRODUCT($D$7:$G$7,D16:G16) | K16: =N(H16)*N(I16) | L16: =N(H16)*N(J16) | M16: =K16+L16 | N16: BL-W02
A17: 8A.T | B17: Windows - total structural opening area | C17: m2 | E17: 3.126 | G17: 22.001 | H17: =SUMPRODUCT($D$7:$G$7,D17:G17) | M17: not priced
A18: 8B External doors (NRM2 25 - package WIN)
A19: 8B.1 | B19: Aluminium bi-fold / glazed doors (PPC, low threshold), 3,445 x 2,076 so (L1-D01, master suite to the covered terrace) | C19: nr | G19: 1 | H19: =SUMPRODUCT($D$7:$G$7,D19:G19) | K19: =N(H19)*N(I19) | L19: =N(H19)*N(J19) | M19: =K19+L19 | N19: PAS 24 / Secured by Design per the warrant
A20: 8B.2 | B20: Aluminium bi-fold / glazed doors (PPC, low threshold), 3,445 x 2,075 so (L1-G02, dining, in the glazing gap under the glazed gable) | C20: nr | G20: 1 | H20: =SUMPRODUCT($D$7:$G$7,D20:G20) | K20: =N(H20)*N(I20) | L20: =N(H20)*N(J20) | M20: =K20+L20 | N20: PAS 24 / Secured by Design per the warrant
A21: 8B.3 | B21: Aluminium glazed door + sidelight (PPC, low threshold), 1,641 x 2,030 so (BL-D02, laundry - threshold 620 above the basement FFL as drawn) | C21: nr | E21: 1 | H21: =SUMPRODUCT($D$7:$G$7,D21:G21) | K21: =N(H21)*N(I21) | L21: =N(H21)*N(J21) | M21: =K21+L21 | N21: PAS 24 / Secured by Design per the warrant
A22: 8C Glazed screens - stair (NRM2 25 - package WIN)
A23: 8C.1 | B23: Link stair glazed screen (aluminium PPC, mullions <= 1000, insulated spandrel at 0 slab zones): L1-G03b, 1,330 x 2,286 (2 panes) | C23: m2 | G23: 3.04 | H23: =SUMPRODUCT($D$7:$G$7,D23:G23) | K23: =N(H23)*N(I23) | L23: =N(H23)*N(J23) | M23: =K23+L23 | N23: 1 nr
A24: 8C.2 | B24: Link stair glazed screen (aluminium PPC, mullions <= 1000, insulated spandrel at 1 slab zone): BL-G04, 1,040 x 5,586 (2 panes, insulated spandrel at the GF slab zone) | C24: m2 | E24: 5.809 | H24: =SUMPRODUCT($D$7:$G$7,D24:G24) | K24: =N(H24)*N(I24) | L24: =N(H24)*N(J24) | M24: =K24+L24 | N24: 1 nr
A25: 8D Raked feature glazing screens to the vaulted roof / glazed gables (NRM2 25 - package GLZ; GLAZING SPECIALIST)
B26: Tom 20.10: "openings in the raked openings need to be raked, like a feature window" - aluminium PPC screens whose heads follow the rafter soffit / gable (KBW raked_screen: mullions <= 1,000, transom 2,100 where the screen passes it, DGU cut to the rake, toughened / laminated). Areas re-measured here from each screen's head profile: the fbw_fit.json "glass_m2" figures UNDER-REPORT the glass by about half (the fit script averaged the pane polygon vertex heights) - Schedule B lists both. Design, wind loading, the structural mullions and the glazed-gable support are by the glazing specialist / engineer.
A27: 8D.1 | B27: Raked screen L1-G01, 2,205 wide, sill 0, head to 4,517 (Raked aluminium feature glazing screen to the Roof L slope): 3 bays, 6 DGU panes | C27: m2 | G27: 7.539 | H27: =SUMPRODUCT($D$7:$G$7,D27:G27) | K27: =N(H27)*N(I27) | L27: =N(H27)*N(J27) | M27: =K27+L27 | N27: Gross 7.54 m2; glass ~6.33 m2 (fbw_fit reported 6.33)
A28: 8D.2 | B28: Raked screen L1-G03a, 2,367 wide, sill 0, head to 4,475 (Raked aluminium feature glazing screen to the Roof R gable): 3 bays, 6 DGU panes | C28: m2 | G28: 7.803 | H28: =SUMPRODUCT($D$7:$G$7,D28:G28) | K28: =N(H28)*N(I28) | L28: =N(H28)*N(J28) | M28: =K28+L28 | N28: Gross 7.80 m2; glass ~6.60 m2 (fbw_fit reported 6.85)
A29: 8D.3 | B29: Raked screen L1-G05, 2,197 wide, sill -960, head to 4,509 (Raked aluminium feature glazing screen to the Roof L slope): 3 bays, 6 DGU panes | C29: m2 | G29: 9.612 | H29: =SUMPRODUCT($D$7:$G$7,D29:G29) | K29: =N(H29)*N(I29) | L29: =N(H29)*N(J29) | M29: =K29+L29 | N29: Gross 9.61 m2; glass ~8.17 m2 (fbw_fit reported 8.17)
A30: 8D.4 | B30: Raked screen L1-G02R, 3,445 wide, sill 2,075, head to 5,963 (Raked aluminium feature glazing screen to the Roof R gable): 4 bays, 4 DGU panes | C30: m2 | G30: 8.718 | H30: =SUMPRODUCT($D$7:$G$7,D30:G30) | K30: =N(H30)*N(I30) | L30: =N(H30)*N(J30) | M30: =K30+L30 | N30: Gross 8.72 m2; glass ~7.59 m2 (fbw_fit reported 7.54)
A31: 8D.T | B31: Raked screens - DGU glass area (re-measured, for the glazing specialist) | C31: m2 | G31: 28.689 | H31: =SUMPRODUCT($D$7:$G$7,D31:G31) | M31: not priced | N31: Not a separate priced item
A32: 8E Guarding, garage door and items not modelled (PROVISIONAL)
A33: 8E.1 | B33: Guarding to the floor-length windows / corner screen where the outside ground is more than 600 mm below FFL (Standard 4.4 pedestrian protective barriers): laminated fixed lower pane / Juliet balustrade - W01-W08 (front, east, west), G03a | C33: nr | G33: 9 | H33: =SUMPRODUCT($D$7:$G$7,D33:G33) | K33: =N(H33)*N(I33) | L33: =N(H33)*N(J33) | M33: =K33+L33 | N33: PROVISIONAL - architect; ground levels scaled from the elevations
A34: 8E.2 | B34: Garage sectional overhead door 4,555 x 2,394 (BL-D01), insulated, motor + controls, incl. guides / fixings to the ICF reveals | C34: nr | E34: 1 | H34: =SUMPRODUCT($D$7:$G$7,D34:G34) | K34: =N(H34)*N(I34) | L34: =N(H34)*N(J34) | M34: =K34+L34 | N34: PROVISIONAL - garage door supplier (not fitted in the model); lintel by the engineer
A35: 8E.3 | B35: Basement pool hall / hall glazed screen (drawn, NOT modelled): aluminium screen, size TBC | C35: item | K35: =IF(ISNUMBER(H35),H35,1)*N(I35) | L35: =IF(ISNUMBER(H35),H35,1)*N(J35) | M35: =K35+L35 | N35: Lump sum - the rate entered is the amount. PROVISIONAL - not measured
A37: PACKAGE SUMMARY - Bill 8 Glazing, External Doors, Raked Feature Screens & Garage Door (package WIN / GLZ; amounts by others, excl. VAT)
A38: Section | B38: Description | K38: Supply £ | L38: Install £ | M38: Total £
A39: 8A | B39: Windows - UPVC casements (NRM2 25 - package WIN; window supplier) | K39: =SUM(K9:K17) | L39: =SUM(L9:L17) | M39: =SUM(M9:M17)
A40: 8B | B40: External doors (NRM2 25 - package WIN) | K40: =SUM(K19:K21) | L40: =SUM(L19:L21) | M40: =SUM(M19:M21)
A41: 8C | B41: Glazed screens - stair (NRM2 25 - package WIN) | K41: =SUM(K23:K24) | L41: =SUM(L23:L24) | M41: =SUM(M23:M24)
A42: 8D | B42: Raked feature glazing screens to the vaulted roof / glazed gables (NRM2 25 - package GLZ; GLAZING SPECIALIST) | K42: =SUM(K26:K31) | L42: =SUM(L26:L31) | M42: =SUM(M26:M31)
A43: 8E | B43: Guarding, garage door and items not modelled (PROVISIONAL) | K43: =SUM(K33:K35) | L43: =SUM(L33:L35) | M43: =SUM(M33:M35)
A44: PACKAGE TOTAL - Bill 8, carried to the Cover overview | K44: =SUM(K39:K43) | L44: =SUM(L39:L43) | M44: =SUM(M39:M43)
A45: Pale-yellow cells are the only inputs (Supply rate, Install rate). Amounts, subtotals and totals are formulas; the sheet is protected without a password (Review > Unprotect Sheet). Amounts exclude VAT and are NOT part of the Nudura ICF price.

Sheet Bill 9 Waterproofing Pool
C1: Bill 9 - Basement Waterproofing (BS 8102) & ICF Pool Tank - PROVISIONAL
C2: Provisional quantities for the BS 8102 waterproofing specialist (Types A / B / C) and the pool specialist (pool tank finishes, coping, plant). [NRM2 17 / package WPF / POOL]
A4: DISCLAIMER: This information is supplied in good faith for guidance and coordination only. It is not part of the Nudura ICF price and must be checked and verified by the appropriate professional (quantity surveyor, designer, engineer or supplier) before use. Only the Nudura ICF formwork and associated accessories are included in our price. Quantities are measured from the BuildEase quotation model of the Foote McBride planning drawings (C2523 PP 01 001-008, raster, no sections / dimensions / levels - heights scaled from the elevations); no allowance for waste is included unless stated. Quantity columns are the model levels P / BL / FB / L1; the Site total is their sum. Rates and amounts are by others.
A6: Ref | B6: Description | C6: Unit | D6: P pool tank | E6: BL basement | F6: FB master footing | G6: L1 ground floor | H6: Site total qty | I6: Supply rate £ | J6: Install rate £ | K6: Supply £ | L6: Install £ | M6: Line total £ | N6: Notes
B7: One building - quantity per level (Site total = sum of the levels) | D7: 1 | E7: 1 | F7: 1 | G7: 1 | H7: =SUM(D7:G7) | N7: Levels: P = pool tank: 3 courses 10in Std, -5,029 to -3,658 (on the pool base); BL = basement: 8 courses 10in Std, FFL -3,300 - garage, laundry, stores, pool hall; FB = master-suite footing: 2 courses 6in XR35, -914 to 0 (no basement under it); L1 = ground floor: 14 courses 6in XR35 incl. the raked gables, vaulted ceilings
A8: 9A BS 8102:2022 waterproofing - PROVISIONAL (NRM2 17 - package WPF; SPECIALIST WATERPROOFING DESIGNER)
B9: The basement contains habitable space and a pool hall: Grade 3 environment - BS 8102 recommends combined protection (e.g. Type A external barrier + Type B water-resisting structure, and / or a Type C cavity drain). The specialist designer chooses the system; the quantities below are the measured surfaces for each type so it can be priced either way. Below-ground ICF faces = the modelled outer EPS faces less the exposed faces of Bill 1 (Schedule A).
A10: 9A.1 | B10: Type A: external waterproofing membrane bonded to the below-ground ICF EPS faces (ICF-compatible, solvent-free), lapped onto the raft toe | C10: m2 | D10: 41.996 | E10: 125.392 | F10: 8.915 | H10: =SUMPRODUCT($D$7:$G$7,D10:G10) | K10: =N(H10)*N(I10) | L10: =N(H10)*N(J10) | M10: =K10+L10 | N10: Order guide +15% = 202.7
A11: 9A.2 | B11: Protection board / drainage composite over the membrane before backfill | C11: m2 | D11: 41.996 | E11: 125.392 | F11: 8.915 | H11: =SUMPRODUCT($D$7:$G$7,D11:G11) | K11: =N(H11)*N(I11) | L11: =N(H11)*N(J11) | M11: =K11+L11
A12: 9A.3 | B12: Type B: water-resisting admixture / mix for the pool base + pool tank cores and the raft + basement wall cores | C12: m3 | D12: 30.192 | E12: 108.717 | H12: =SUMPRODUCT($D$7:$G$7,D12:G12) | K12: =N(H12)*N(I12) | L12: =N(H12)*N(J12) | M12: =K12+L12 | N12: Raft 53.2 + pool base 17.87 + ICF cores P 12.3 / BL 55.5 (geometric)
A13: 9A.4 | B13: Hydrophilic / crystalline waterstop at the base-to-wall construction joints (pool base / pool walls; raft / basement walls) | C13: m | D13: 29.104 | E13: 60.382 | H13: =SUMPRODUCT($D$7:$G$7,D13:G13) | K13: =N(H13)*N(I13) | L13: =N(H13)*N(J13) | M13: =K13+L13 | N13: Wall centre-line lengths
A14: 9A.5 | B14: Type C: cavity drain membrane to the basement inner wall faces (if specified) incl. fixings / plugs and sealing to the floor membrane | C14: m2 | E14: 158.695 | H14: =SUMPRODUCT($D$7:$G$7,D14:G14) | K14: =N(H14)*N(I14) | L14: =N(H14)*N(J14) | M14: =K14+L14
A15: 9A.6 | B15: Type C: cavity drain floor membrane under the insulation / screed (if specified) | C15: m2 | E15: 140.32 | H15: =SUMPRODUCT($D$7:$G$7,D15:G15) | K15: =N(H15)*N(I15) | L15: =N(H15)*N(J15) | M15: =K15+L15
A16: 9A.7 | B16: Type C: perimeter drainage channel to the sump | C16: m | E16: 58.283 | H16: =SUMPRODUCT($D$7:$G$7,D16:G16) | K16: =N(H16)*N(I16) | L16: =N(H16)*N(J16) | M16: =K16+L16
A17: 9A.8 | B17: Sump chamber with twin pumps, high-level alarm and battery back-up, discharge to the drainage | C17: nr | E17: 1 | H17: =SUMPRODUCT($D$7:$G$7,D17:G17) | K17: =N(H17)*N(I17) | L17: =N(H17)*N(J17) | M17: =K17+L17 | N17: Specialist; maintenance access
A18: 9A.9 | B18: Perimeter land drain at raft level (perforated pipe in clean stone, geotextile wrap) incl. rodding points | C18: m | E18: 58.844 | H18: =SUMPRODUCT($D$7:$G$7,D18:G18) | K18: =N(H18)*N(I18) | L18: =N(H18)*N(J18) | M18: =K18+L18 | N18: Outer perimeter of the basement walls incl. the rear retaining wall
A19: 9A.10 | B19: BS 8102 waterproofing design, inspection and insurance-backed guarantee (specialist) | C19: item | K19: =IF(ISNUMBER(H19),H19,1)*N(I19) | L19: =IF(ISNUMBER(H19),H19,1)*N(J19) | M19: =K19+L19 | N19: Lump sum - the rate entered is the amount. Specialist
A20: 9B ICF pool tank (NRM2 - package POOL; POOL SPECIALIST - PROVISIONAL)
B21: Pool tank in ICF (Tom 20.10): outline only on the drawings - 3.9 x 9.8 m inside, ~1.5 m water depth ASSUMED (pool floor ~-4,800), walls 3 courses from -5,029 on the pool base; the basement floor build-up forms the coping. Structure, tanking, finishes and plant by the pool specialist / engineer.
A22: 9B.1 | B22: Pool tank wall inner faces (ICF EPS): pool tanking / render system + tiling or liner | C22: m2 | D22: 37.837 | H22: =SUMPRODUCT($D$7:$G$7,D22:G22) | K22: =N(H22)*N(I22) | L22: =N(H22)*N(J22) | M22: =K22+L22 | N22: Modelled inner faces of the pool tank
A23: 9B.2 | B23: Pool floor: screed to falls / profile + tanking + tiling or liner | C23: m2 | D23: 38.749 | H23: =SUMPRODUCT($D$7:$G$7,D23:G23) | K23: =N(H23)*N(I23) | L23: =N(H23)*N(J23) | M23: =K23+L23 | N23: 3.9 x 9.8 inside
A24: 9B.3 | B24: Pool coping / edge detail at the basement floor level | C24: m | D24: 27.554 | H24: =SUMPRODUCT($D$7:$G$7,D24:G24) | K24: =N(H24)*N(I24) | L24: =N(H24)*N(J24) | M24: =K24+L24
A25: 9B.4 | B25: Pool plant, filtration, heating, dehumidification / ventilation of the pool hall, pipework through the ICF (sleeves) | C25: item | K25: =IF(ISNUMBER(H25),H25,1)*N(I25) | L25: =IF(ISNUMBER(H25),H25,1)*N(J25) | M25: =K25+L25 | N25: Lump sum - the rate entered is the amount. PC sum - pool specialist / M&E; not measured
A27: PACKAGE SUMMARY - Bill 9 Basement Waterproofing (BS 8102) & ICF Pool Tank - PROVISIONAL (package WPF / POOL; amounts by others, excl. VAT)
A28: Section | B28: Description | K28: Supply £ | L28: Install £ | M28: Total £
A29: 9A | B29: BS 8102:2022 waterproofing - PROVISIONAL (NRM2 17 - package WPF; SPECIALIST WATERPROOFING DESIGNER) | K29: =SUM(K9:K19) | L29: =SUM(L9:L19) | M29: =SUM(M9:M19)
A30: 9B | B30: ICF pool tank (NRM2 - package POOL; POOL SPECIALIST - PROVISIONAL) | K30: =SUM(K21:K25) | L30: =SUM(L21:L25) | M30: =SUM(M21:M25)
A31: PACKAGE TOTAL - Bill 9, carried to the Cover overview | K31: =SUM(K29:K30) | L31: =SUM(L29:L30) | M31: =SUM(M29:M30)
A32: Pale-yellow cells are the only inputs (Supply rate, Install rate). Amounts, subtotals and totals are formulas; the sheet is protected without a password (Review > Unprotect Sheet). Amounts exclude VAT and are NOT part of the Nudura ICF price.

Sheet Schedule A Areas
C1: Schedule A - Areas: Exposed Faces, Floors, Ceilings and Roof
C2: Exposed external faces (ground lines scaled off the elevation renders, +-150), ICF face areas (component export), floor / ceiling / roof areas. Not priced.
A4: DISCLAIMER: This information is supplied in good faith for guidance and coordination only. It is not part of the Nudura ICF price and must be checked and verified by the appropriate professional (quantity surveyor, designer, engineer or supplier) before use. Only the Nudura ICF formwork and associated accessories are included in our price. Quantities are measured from the BuildEase quotation model of the Foote McBride planning drawings (C2523 PP 01 001-008, raster, no sections / dimensions / levels - heights scaled from the elevations); no allowance for waste is included unless stated. Quantity columns are the model levels P / BL / FB / L1; the Site total is their sum. Rates and amounts are by others.
A6: Level | B6: Item | C6: Source | D6: Length m | E6: Depth m | F6: Area m2
A7: BL | B7: Exposed external face: East (pool) wall, outer face x -15.9, y -15.9 to 15,620.9 | C7: east elevation: ground ~1,231 below FFL (pool window sills -1,236) | D7: 15.64 | E7: 1.231 | F7: 19.25
A8: BL | B8: Exposed external face: Front of the bed-3 wing, outer face y -15.9, x -15.9 to 5,178.7 | C8: front elevation: ground / entrance path 0.90-1.11 below FFL | D8: 5.19 | E8: 1.017 | F8: 5.28
A9: BL | B9: Exposed external face: Stair pier, front-west face x 7,731.5, y 1,060-2,610 (garage apron) | C9: front elevation: apron ~3.26 below FFL | D9: 1.55 | E9: 3.263 | F9: 5.06
A10: BL | B10: Exposed external face: Garage front, outer face y 3,634.1, x 7,360-15,075.9 | C10: front elevation: apron 3.22-3.31 below FFL | D10: 7.72 | E10: 3.263 | F10: 25.18
A11: BL | B11: Exposed external face: West wall, outer face x 15,075.9, y 3,634.1-15,620.9 | C11: west elevation: 3.31 at the front falling to 2.71 (laundry threshold -2,680) | D11: 11.99 | E11: 2.825 | F11: 33.86
A12: BL | B12: Exposed external face: Rear wall behind the hall / dining / kitchen, y 15,620.9, x 5,178.7-15,075.9 | C12: rear elevation: terrace at ~DPC - 150 band only | D12: 9.9 | E12: 0.15 | F12: 1.48
A13: FB | B13: Exposed external face: Master suite east wall, outer face x 0, y 15,620.9-20,445 | C13: east elevation: 1.12 falling to 0.22 below FFL | D13: 4.82 | E13: 0.645 | F13: 3.11
A14: FB | B14: Exposed external face: Master suite rear wall, y 20,445, x 0-5,162.8 | C14: rear elevation: DPC band | D14: 5.16 | E14: 0.15 | F14: 0.77
A15: FB | B15: Exposed external face: Master suite west wall to the covered terrace, x 5,162.8 | C15: west elevation: terrace ~DPC | D15: 4.82 | E15: 0.15 | F15: 0.72
A16: BL | B16: Less basement openings (garage door, pool windows, laundry door) - all above ground | C16: KB_spec.json | F16: -17.36
A17: L1 | B17: GF external ICF face, FFL to the plate / gable rakes (component outer faces less the hall stub) | C17: KB_components.json | F17: 161.98
A18: BL | B18: Below-ground ICF outer faces (Type A tanking) = outer faces - exposed - interior faces | C18: KB_components.json | F18: 125.39
A19: P | B19: Pool tank outer faces (all below ground) | C19: KB_components.json | F19: 42
A20: FB | B20: Master-suite footing outer faces below ground | C20: KB_components.json | F20: 8.91
A21: BL | B21: Basement floor build-up (internal, incl. garage, excl. pool hall) | C21: KB_slabs.json bl_floor | F21: 140.32
A22: BL | B22: Garage (x 7,637-14,689, y 4,022-11,066) | C22: partition layout | F22: 49.05
A23: BL | B23: Basement rooms ceiling (bl_floor - garage - partition footprints) | C23: derived | F23: 87.54
A24: BL | B24: Pool hall (x 372-4,698, y 5,201-15,234) | C24: KB_slabs.json raft hole | F24: 43.4
A25: P | B25: Pool tank inside (3.9 x 9.8) | C25: KB_spec dims | F25: 38.75
A26: L1 | B26: GF slab outline less half the ICF (inner faces) | C26: KB_slabs.json gf | F26: 177.58
A27: FB | B27: Master suite (inside the FB footing walls) | C27: KB_slabs.json ms | F27: 19.89
... A34: L1 | B34: Roof covering on the slope | C34: derived | F34: 367.06
A36: Depth = mean depth of finished ground below GF FFL along the face (capped at the wall height); the BL / FB exposed areas feed Bill 1A.2 / 1A.3.

Sheet Schedule B Openings
C1: Schedule B - Openings & Glazing Schedule (spec openings + BuildEase window fit)
C2: From KB_spec.json (13 ICF openings) and fbw_fit.json (screens in the glazing gaps). Raked screens: gross / glass re-measured from the head profiles. Not priced.
A4: DISCLAIMER: This information is supplied in good faith for guidance and coordination only. It is not part of the Nudura ICF price and must be checked and verified by the appropriate professional (quantity surveyor, designer, engineer or supplier) before use. Only the Nudura ICF formwork and associated accessories are included in our price. Quantities are measured from the BuildEase quotation model of the Foote McBride planning drawings (C2523 PP 01 001-008, raster, no sections / dimensions / levels - heights scaled from the elevations); no allowance for waste is included unless stated. Quantity columns are the model levels P / BL / FB / L1; the Site total is their sum. Rates and amounts are by others.
A6: Level | B6: Ref | C6: Type | D6: Style | E6: W mm | F6: H mm | G6: Sill mm | H6: Area m2 | I6: Glass m2 (re-measured) | J6: Glass m2 (fbw_fit) | K6: Description
A7: L1 | B7: L1-W01 | C7: window | D7: window | E7: 1255 | F7: 2075 | G7: 0 | H7: 2.6 | K7: UPVC casement window, 2 lights (2 opening)
A8: L1 | B8: L1-W02 | C8: window | D8: window | E8: 1250 | F8: 2075 | G8: 0 | H8: 2.59 | K8: UPVC casement window, 2 lights (2 opening)
A9: L1 | B9: L1-W03 | C9: window | D9: window | E9: 2035 | F9: 2075 | G9: 0 | H9: 4.22 | K9: UPVC casement window, 3 lights (2 opening)
A10: L1 | B10: L1-W04 | C10: window | D10: window | E10: 1050 | F10: 2075 | G10: 0 | H10: 2.18 | K10: UPVC casement window, 1 light (1 opening)
A11: L1 | B11: L1-D01 | C11: door | D11: double_door | E11: 3445 | F11: 2075 | G11: 0 | H11: 7.15 | K11: Aluminium bi-fold / glazed doors (PPC, low threshold)
A12: L1 | B12: L1-W05 | C12: window | D12: window | E12: 1250 | F12: 2075 | G12: 0 | H12: 2.59 | K12: UPVC casement window, 2 lights (2 opening)
A13: L1 | B13: L1-W06 | C13: window | D13: window | E13: 1240 | F13: 2075 | G13: 0 | H13: 2.57 | K13: UPVC casement window, 2 lights (2 opening)
A14: L1 | B14: L1-W07 | C14: window | D14: window | E14: 1255 | F14: 2075 | G14: 0 | H14: 2.6 | K14: UPVC casement window, 2 lights (2 opening)
A15: L1 | B15: L1-W08 | C15: window | D15: window | E15: 1255 | F15: 2075 | G15: 0 | H15: 2.6 | K15: UPVC casement window, 2 lights (2 opening)
A16: BL | B16: BL-D01 | C16: door | D16: garage door (supplier) | E16: 4555 | F16: 2394 | G16: -3300 | H16: 10.9 | K16: garage door 4.55 x 2.39 (front elevation head 906 below GF FFL)
A17: BL | B17: BL-W01 | C17: window | D17: window | E17: 1735 | F17: 897 | G17: -1236 | H17: 1.56 | K17: UPVC casement window, 3 lights (2 opening)
A18: BL | B18: BL-W02 | C18: window | D18: window | E18: 1745 | F18: 897 | G18: -1236 | H18: 1.57 | K18: UPVC casement window, 3 lights (2 opening)
A19: BL | B19: BL-D02 | C19: door | D19: glazed_door | E19: 1640 | F19: 2030 | G19: -2680 | H19: 3.33 | K19: Aluminium glazed door + sidelight (PPC, low threshold)
A20: L1 | B20: L1-G01 | C20: screen | D20: raked_screen | E20: 2205 | F20: 2286 | G20: 0 | H20: 7.54 | I20: 6.33 | J20: 6.33 | K20: Raked aluminium feature glazing screen to the Roof L slope (PPC, DGU,
A21: L1 | B21: L1-G02 | C21: screen | D21: double_door | E21: 3445 | F21: 2075 | G21: 0 | H21: 7.15 | K21: Aluminium bi-fold / glazed doors (PPC, low threshold)
A22: L1 | B22: L1-G02R | C22: screen | D22: raked_screen | E22: 3445 | F22: 3900 | G22: 2075 | H22: 8.72 | I22: 7.59 | J22: 7.54 | K22: Raked aluminium feature glazing screen to the Roof R gable (PPC, DGU,
A23: L1 | B23: L1-G03a | C23: screen | D23: raked_screen | E23: 2367 | F23: 2286 | G23: 0 | H23: 7.8 | I23: 6.6 | J23: 6.85 | K23: Raked aluminium feature glazing screen to the Roof R gable (PPC, DGU,
A24: L1 | B24: L1-G03b | C24: screen | D24: stair_screen | E24: 1330 | F24: 2286 | G24: 0 | H24: 3.04 | K24: Link stair glazed screen (aluminium PPC, mullions <= 1000, insulated s
A25: BL | B25: BL-G04 | C25: screen | D25: stair_screen | E25: 1040 | F25: 5586 | G25: 0 | H25: 5.81 | K25: Link stair glazed screen (aluminium PPC, mullions <= 1000, insulated s
A26: L1 | B26: L1-G05 | C26: screen | D26: raked_screen | E26: 2197 | F26: 3246 | G26: -960 | H26: 9.61 | I26: 8.17 | J26: 8.17 | K26: Raked aluminium feature glazing screen to the Roof L slope (PPC, DGU,
A28: Raked screens: H = the ICF gap / screen height at the jamb; the gross area follows the raked head. The fbw_fit glass_m2 under-reports by ~half (see the notes).

Sheet Schedule C Per Level
C1: Schedule C - Key Quantities per Level
C2: Reference only - the bills carry the priced quantities. Not priced.
A4: DISCLAIMER: This information is supplied in good faith for guidance and coordination only. It is not part of the Nudura ICF price and must be checked and verified by the appropriate professional (quantity surveyor, designer, engineer or supplier) before use. Only the Nudura ICF formwork and associated accessories are included in our price. Quantities are measured from the BuildEase quotation model of the Foote McBride planning drawings (C2523 PP 01 001-008, raster, no sections / dimensions / levels - heights scaled from the elevations); no allowance for waste is included unless stated. Quantity columns are the model levels P / BL / FB / L1; the Site total is their sum. Rates and amounts are by others.
A6: Level | B6: ICF outer face m2 | C6: ICF inner face m2 | D6: External finish m2 | E6: Wall linings m2 | F6: Ceilings m2 | G6: Doors nr | H6: Skirting m | I6: Partitions m2
A7: P | B7: 42 | C7: 37.84 | D7: 0 | E7: 0 | F7: 0 | G7: 0 | H7: 0 | I7: 0
A8: BL | B8: 209.01 | C8: 195.51 | D8: 72.76 | E8: 292.08 | F8: 136.59 | G8: 6 | H8: 68.92 | I8: 93.3
A9: FB | B9: 13.53 | C9: 12.23 | D9: 4.61 | E9: 0 | F9: 0 | G9: 0 | H9: 0 | I9: 0
A10: L1 | B10: 165.91 | C10: 157.92 | D10: 161.98 | E10: 558.59 | F10: 282.55 | G10: 7 | H10: 119.62 | I10: 200.93
A11: Total | B11: =SUM(B7:B10) | C11: =SUM(C7:C10) | D11: =SUM(D7:D10) | E11: =SUM(E7:E10) | F11: =SUM(F7:F10) | G11: =SUM(G7:G10) | H11: =SUM(H7:H10) | I11: =SUM(I7:I10)
A13: ICF faces from the Report Tool component export (588 forms). Ceilings: basement rooms + garage; GF vaulted on the slope.

Sheet Schedule D Partitions
C1: Schedule D - TLSTF Partition Schedule (as built in the model)
C2: From the TLSTF walls / verify / doors / rake / head-restraint / pattress reports (04_Logs/build). Not priced.
A4: DISCLAIMER: This information is supplied in good faith for guidance and coordination only. It is not part of the Nudura ICF price and must be checked and verified by the appropriate professional (quantity surveyor, designer, engineer or supplier) before use. Only the Nudura ICF formwork and associated accessories are included in our price. Quantities are measured from the BuildEase quotation model of the Foote McBride planning drawings (C2523 PP 01 001-008, raster, no sections / dimensions / levels - heights scaled from the elevations); no allowance for waste is included unless stated. Quantity columns are the model levels P / BL / FB / L1; the Site total is their sum. Rates and amounts are by others.
A6: Floor | B6: Wall | C6: Length mm | D6: Height mm | E6: Area m2 | F6: Build-up | G6: Studs | H6: Members | I6: Door openings (mm) | J6: Head clips | K6: Pattress pcs
A7: BF | B7: BF-P01 | C7: 4469 | D7: 2,975 | E7: 13.3 | F7: kb_int_89_600 | G7: 9 | H7: 44 | I7: 830 | J7: 18
A8: BF | B8: BF-P02 | C8: 2489 | D8: 2,975 | E8: 7.4 | F8: kb_int_89_600 | G8: 7 | H8: 30 | J8: 12
A9: BF | B9: BF-P03 | C9: 6390 | D9: 2,975 | E9: 19.01 | F9: kb_int_89_600 | G9: 14 | H9: 54 | J9: 24
A10: BF | B10: BF-P04 | C10: 7096 | D10: 2,975 | E10: 21.11 | F10: kb_int_89_400 | G10: 19 | H10: 86 | I10: 800, 850 | J10: 26 | K10: 16
A11: BF | B11: BF-P05 | C11: 3022 | D11: 2,975 | E11: 8.99 | F11: kb_int_89_600 | G11: 7 | H11: 30 | J11: 12
A12: BF | B12: BF-P06 | C12: 2736 | D12: 2,975 | E12: 8.14 | F12: kb_int_89_600 | G12: 6 | H12: 32 | I12: 850 | J12: 10
A13: BF | B13: BF-P07 | C13: 4123 | D13: 2,975 | E13: 12.27 | F13: kb_int_89_400 | G13: 13 | H13: 61 | I13: 846 | J13: 16 | K13: 18
A14: BF | B14: BF-P08 | C14: 1037 | D14: 2,975 | E14: 3.08 | F14: kb_int_89_600 | G14: 2 | H14: 11 | I14: 850 | J14: 4
A15: GF | B15: GF-P01 | C15: 3270 | D15: 2,439-5,709 | E15: 13.32 | F15: kb_int_89_600 | G15: 7 | H15: 42 | I15: 855
A16: GF | B16: GF-P02 | C16: 2270 | D16: 5,672-5,865 | E16: 13.1 | F16: kb_int_89_600 | G16: 6 | H16: 25
A17: GF | B17: GF-P03 | C17: 1365 | D17: 2,439-3,804 | E17: 4.26 | F17: kb_int_89_400 | G17: 5 | H17: 23 | K17: 8
A18: GF | B18: GF-P04 | C18: 854 | D18: 3,759-3,759 | E18: 3.21 | F18: kb_int_89_600 | G18: 4 | H18: 18
A19: GF | B19: GF-P05 | C19: 972 | D19: 4,750-4,750 | E19: 4.61 | F19: kb_int_89_600 | G19: 3 | H19: 13
A20: GF | B20: GF-P06 | C20: 898 | D20: 4,706-5,604 | E20: 4.63 | F20: kb_int_89_600 | G20: 4 | H20: 18
A21: GF | B21: GF-P07 | C21: 3510 | D21: 5,648-5,648 | E21: 19.83 | F21: kb_int_89_400 | G21: 12 | H21: 64 | K21: 16
A22: GF | B22: GF-P08 | C22: 1409 | D22: 4,717-5,865 | E22: 7.57 | F22: kb_int_89_600 | G22: 6 | H22: 28
A23: GF | B23: GF-P09 | C23: 1231 | D23: 4,806-5,865 | E23: 6.64 | F23: kb_int_89_400 | G23: 7 | H23: 30 | K23: 10
A24: GF | B24: GF-P10 | C24: 6938 | D24: 4,762-4,762 | E24: 33.04 | F24: kb_int_89_400 | G24: 22 | H24: 131 | I24: 850, 850 | K24: 10
A25: GF | B25: GF-P11 | C25: 2928 | D25: 4,762-4,762 | E25: 13.94 | F25: kb_int_89_600 | G25: 6 | H25: 28
A26: GF | B26: GF-P12 | C26: 4485 | D26: 2,439-5,865 | E26: 19.87 | F26: kb_int_89_400 | G26: 16 | H26: 81 | K26: 18
A27: GF | B27: GF-P13 | C27: 334 | D27: 5,472-5,472 | E27: 1.83 | F27: kb_int_89_600 | G27: 3 | H27: 13
A28: GF | B28: GF-P14 | C28: 378 | D28: 5,472-5,472 | E28: 2.07 | F28: kb_int_89_600 | G28: 3 | H28: 13
A29: GF | B29: GF-P15 | C29: 711 | D29: 4,806-5,517 | E29: 3.67 | F29: kb_int_89_600 | G29: 3 | H29: 13
A30: GF | B30: GF-P16 | C30: 4574 | D30: 2,439-5,865 | E30: 20.3 | F30: kb_int_89_400 | G30: 12 | H30: 92 | I30: 680, 680, 762 | K30: 6
A31: GF | B31: GF-P17 | C31: 1365 | D31: 2,439-3,804 | E31: 4.26 | F31: kb_int_89_600 | G31: 4 | H31: 18
A32: GF | B32: GF-P18 | C32: 631 | D32: 3,759-3,759 | E32: 2.37 | F32: kb_int_89_400 | G32: 3 | H32: 13 | K32: 4
A33: GF | B33: GF-P19 | C33: 1605 | D33: 5,664-5,664 | E33: 9.09 | F33: kb_int_89_400 | G33: 5 | H33: 23 | K33: 8
A34: GF | B34: GF-P20 | C34: 3270 | D34: 2,439-5,709 | E34: 13.32 | F34: kb_int_89_400 | G34: 8 | H34: 41 | I34: 680 | K34: 6
A36: BF 8 walls 31.4 m / GF 20 walls 43.0 m = 74.4 m, 13 door openings. GF heights = min-max of the raked head.
